[{"date": "2021-12-01 00:00:00+00:00", "conversions": 10.977524928005888, "ingestion_time": "2021-12-02T12:06:40.737Z", "channel": "GOOGLE", "agency_id": 79, "impressions": 8293, "line_id": "113891829773", "creative_id": "483794209624", "video_view_complete": 2074, "advertiser_id": 82, "account_id": "6472380435", "job_id": 1024, "spend": 1976480000, "video_view_25p": 2696, "clicks": 3058, "video_view_75p": 178, "campaign_id": "11765801249", "video_view_50p": 6288}, {"date": "2021-12-01 00:00:00+00:00", "conversions": 6.1809559585892515, "ingestion_time": "2021-12-02T12:06:40.737Z", "channel": "GOOGLE", "agency_id": 79, "impressions": 9476, "line_id": "113891829773", "creative_id": "483794209624", "video_view_complete": 4729, "advertiser_id": 82, "account_id": "6472380435", "job_id": 1024, "spend": 1976480000, "video_view_25p": 3862, "clicks": 3262, "video_view_75p": 4307, "campaign_id": "11765801249", "video_view_50p": 7568}, {"date": "2021-12-01 00:00:00+00:00", "conversions": 52.81458331264249, "ingestion_time": "2021-12-02T12:06:40.737Z", "channel": "GOOGLE", "agency_id": 79, "impressions": 8889, "line_id": "127284931385", "creative_id": "549225733883", "video_view_complete": 2622, "advertiser_id": 82, "account_id": "6472380435", "job_id": 1024, "spend": 1976480000, "video_view_25p": 938, "clicks": 4754, "video_view_75p": 9033, "campaign_id": "14823424775", "video_view_50p": 1951}, {"date": "2021-12-01 00:00:00+00:00", "conversions": 36.232944012818535, "ingestion_time": "2021-12-02T12:06:40.737Z", "channel": "GOOGLE", "agency_id": 79, "impressions": 9428, "line_id": "127284931385", "creative_id": "549225733883", "video_view_complete": 7577, "advertiser_id": 82, "account_id": "6472380435", "job_id": 1024, "spend": 1976480000, "video_view_25p": 9460, "clicks": 5954, "video_view_75p": 4552, "campaign_id": "14823424775", "video_view_50p": 8295}, {"date": "2021-12-01 00:00:00+00:00", "conversions": 24.68361526791799, "ingestion_time": "2021-12-02T12:06:40.737Z", "channel": "GOOGLE", "agency_id": 79, "impressions": 3738, "line_id": "127649136469", "creative_id": "550546565026", "video_view_complete": 1350, "advertiser_id": 82, "account_id": "6472380435", "job_id": 1024, "spend": 1976480000, "video_view_25p": 9366, "clicks": 4157, "video_view_75p": 2666, "campaign_id": "14881489614", "video_view_50p": 8493}, {"date": "2021-12-01 00:00:00+00:00", "conversions": 59.719293565002616, "ingestion_time": "2021-12-02T12:06:40.737Z", "channel": "GOOGLE", "agency_id": 79, "impressions": 2826, "line_id": "127649136469", "creative_id": "550546565026", "video_view_complete": 4826, "advertiser_id": 82, "account_id": "6472380435", "job_id": 1024, "spend": 1976480000, "video_view_25p": 6933, "clicks": 8049, "video_view_75p": 1489, "campaign_id": "14881489614", "video_view_50p": 7991}, {"date": "2021-12-01 00:00:00+00:00", "conversions": 0.6635443637206029, "ingestion_time": "2021-12-02T12:06:40.737Z", "channel": "GOOGLE", "agency_id": 79, "impressions": 3943, "line_id": "127284931385", "creative_id": "549225733886", "video_view_complete": 2840, "advertiser_id": 82, "account_id": "6472380435", "job_id": 1024, "spend": 1976480000, "video_view_25p": 632, "clicks": 544, "video_view_75p": 1456, "campaign_id": "14823424775", "video_view_50p": 5472}, {"date": "2021-12-01 00:00:00+00:00", "conversions": 50.93169916813382, "ingestion_time": "2021-12-02T12:06:40.737Z", "channel": "GOOGLE", "agency_id": 79, "impressions": 546, "line_id": "127284931385", "creative_id": "549225733886", "video_view_complete": 2223, "advertiser_id": 82, "account_id": "6472380435", "job_id": 1024, "spend": 1976480000, "video_view_25p": 6111, "clicks": 9807, "video_view_75p": 825, "campaign_id": "14823424775", "video_view_50p": 9801}, {"date": "2021-12-01 00:00:00+00:00", "conversions": 58.19607959214086, "ingestion_time": "2021-12-02T12:06:40.737Z", "channel": "GOOGLE", "agency_id": 79, "impressions": 5061, "line_id": "127284931385", "creative_id": "549225733877", "video_view_complete": 450, "advertiser_id": 82, "account_id": "6472380435", "job_id": 1024, "spend": 1976480000, "video_view_25p": 2207, "clicks": 7456, "video_view_75p": 1757, "campaign_id": "14823424775", "video_view_50p": 9107}, {"date": "2021-12-01 00:00:00+00:00", "conversions": 74.66765943270917, "ingestion_time": "2021-12-02T12:06:40.737Z", "channel": "GOOGLE", "agency_id": 79, "impressions": 8086, "line_id": "127284931385", "creative_id": "549225733877", "video_view_complete": 4915, "advertiser_id": 82, "account_id": "6472380435", "job_id": 1024, "spend": 1976480000, "video_view_25p": 9407, "clicks": 1945, "video_view_75p": 2345, "campaign_id": "14823424775", "video_view_50p": 2040}, {"date": "2021-12-01 00:00:00+00:00", "conversions": 81.85652031401021, "ingestion_time": "2021-12-02T12:06:40.737Z", "channel": "FACEBOOK", "agency_id": 79, "impressions": 5950, "line_id": "23849725967160369", "creative_id": "23849725967310369", "video_view_complete": 3287, "advertiser_id": 82, "account_id": "act_903970073442940", "job_id": 1024, "spend": 1976480000, "video_view_25p": 521, "clicks": 3508, "video_view_75p": 8557, "campaign_id": "23849725966810369", "video_view_50p": 3431}, {"date": "2021-12-01 00:00:00+00:00", "conversions": 53.99449965648317, "ingestion_time": "2021-12-02T12:06:40.737Z", "channel": "FACEBOOK", "agency_id": 79, "impressions": 4016, "line_id": "23849725967160369", "creative_id": "23849725967310369", "video_view_complete": 4920, "advertiser_id": 82, "account_id": "act_903970073442940", "job_id": 1024, "spend": 1976480000, "video_view_25p": 5726, "clicks": 6329, "video_view_75p": 5011, "campaign_id": "23849725966810369", "video_view_50p": 4014}, {"date": "2021-12-01 00:00:00+00:00", "conversions": 72.03335305303816, "ingestion_time": "2021-12-02T12:06:40.737Z", "channel": "FACEBOOK", "agency_id": 79, "impressions": 7458, "line_id": "23846437463260369", "creative_id": "23846437463280369", "video_view_complete": 5068, "advertiser_id": 82, "account_id": "act_903970073442940", "job_id": 1024, "spend": 1976480000, "video_view_25p": 3543, "clicks": 5296, "video_view_75p": 8426, "campaign_id": "23846437463240369", "video_view_50p": 5845}, {"date": "2021-12-01 00:00:00+00:00", "conversions": 66.12131127611902, "ingestion_time": "2021-12-02T12:06:40.737Z", "channel": "FACEBOOK", "agency_id": 79, "impressions": 6477, "line_id": "23846437463260369", "creative_id": "23846437463280369", "video_view_complete": 7958, "advertiser_id": 82, "account_id": "act_903970073442940", "job_id": 1024, "spend": 1976480000, "video_view_25p": 5170, "clicks": 3431, "video_view_75p": 7614, "campaign_id": "23846437463240369", "video_view_50p": 3246}, {"date": "2021-12-01 00:00:00+00:00", "conversions": 58.453471243142374, "ingestion_time": "2021-12-02T12:06:40.737Z", "channel": "FACEBOOK", "agency_id": 79, "impressions": 7959, "line_id": "23849765193950369", "creative_id": "23849765194020369", "video_view_complete": 2097, "advertiser_id": 82, "account_id": "act_903970073442940", "job_id": 1024, "spend": 1976480000, "video_view_25p": 7002, "clicks": 3022, "video_view_75p": 6109, "campaign_id": "23849765193560369", "video_view_50p": 5524}, {"date": "2021-12-01 00:00:00+00:00", "conversions": 60.58206528581289, "ingestion_time": "2021-12-02T12:06:40.737Z", "channel": "FACEBOOK", "agency_id": 79, "impressions": 4329, "line_id": "23849765193950369", "creative_id": "23849765194020369", "video_view_complete": 952, "advertiser_id": 82, "account_id": "act_903970073442940", "job_id": 1024, "spend": 1976480000, "video_view_25p": 3374, "clicks": 6296, "video_view_75p": 4448, "campaign_id": "23849765193560369", "video_view_50p": 1875}, {"date": "2021-12-01 00:00:00+00:00", "conversions": 55.233244871392415, "ingestion_time": "2021-12-02T12:06:40.737Z", "channel": "FACEBOOK", "agency_id": 79, "impressions": 9629, "line_id": "23845998298820213", "creative_id": "23845998784140213", "video_view_complete": 5353, "advertiser_id": 82, "account_id": "act_3427969697428048", "job_id": 1024, "spend": 1976480000, "video_view_25p": 8226, "clicks": 371, "video_view_75p": 6329, "campaign_id": "23845998298760213", "video_view_50p": 2879}, {"date": "2021-12-01 00:00:00+00:00", "conversions": 90.3766131352991, "ingestion_time": "2021-12-02T12:06:40.737Z", "channel": "FACEBOOK", "agency_id": 79, "impressions": 6435, "line_id": "23845998298820213", "creative_id": "23845998784140213", "video_view_complete": 7167, "advertiser_id": 82, "account_id": "act_3427969697428048", "job_id": 1024, "spend": 1976480000, "video_view_25p": 7698, "clicks": 1368, "video_view_75p": 5508, "campaign_id": "23845998298760213", "video_view_50p": 5319}, {"date": "2021-12-01 00:00:00+00:00", "conversions": 91.55649841793772, "ingestion_time": "2021-12-02T12:06:40.737Z", "channel": "FACEBOOK", "agency_id": 79, "impressions": 6571, "line_id": "23849783566440369", "creative_id": "23849783566450369", "video_view_complete": 4644, "advertiser_id": 82, "account_id": "act_903970073442940", "job_id": 1024, "spend": 1976480000, "video_view_25p": 9520, "clicks": 3528, "video_view_75p": 9051, "campaign_id": "23849783518160369", "video_view_50p": 5501}, {"date": "2021-12-01 00:00:00+00:00", "conversions": 97.13113951300963, "ingestion_time": "2021-12-02T12:06:40.737Z", "channel": "FACEBOOK", "agency_id": 79, "impressions": 8095, "line_id": "23849783566440369", "creative_id": "23849783566450369", "video_view_complete": 3108, "advertiser_id": 82, "account_id": "act_903970073442940", "job_id": 1024, "spend": 1976480000, "video_view_25p": 9274, "clicks": 9664, "video_view_75p": 6723, "campaign_id": "23849783518160369", "video_view_50p": 7448}, {"date": "2021-12-01 00:00:00+00:00", "conversions": 25.819100348170398, "ingestion_time": "2021-12-02T12:06:40.737Z", "channel": "FACEBOOK", "agency_id": 79, "impressions": 7904, "line_id": "23845998298820213", "creative_id": "23845998298890213", "video_view_complete": 3706, "advertiser_id": 82, "account_id": "act_3427969697428048", "job_id": 1024, "spend": 1976480000, "video_view_25p": 6443, "clicks": 8023, "video_view_75p": 8968, "campaign_id": "23845998298760213", "video_view_50p": 6970}, {"date": "2021-12-01 00:00:00+00:00", "conversions": 36.34112513351562, "ingestion_time": "2021-12-02T12:06:40.737Z", "channel": "FACEBOOK", "agency_id": 79, "impressions": 7604, "line_id": "23845998298820213", "creative_id": "23845998298890213", "video_view_complete": 8998, "advertiser_id": 82, "account_id": "act_3427969697428048", "job_id": 1024, "spend": 1976480000, "video_view_25p": 7429, "clicks": 348, "video_view_75p": 2375, "campaign_id": "23845998298760213", "video_view_50p": 5232}, {"date": "2021-12-02 00:00:00+00:00", "conversions": 70.62470162353087, "ingestion_time": "2021-12-02T12:06:40.737Z", "channel": "GOOGLE", "agency_id": 79, "impressions": 551, "line_id": "113891829773", "creative_id": "483794209624", "video_view_complete": 9524, "advertiser_id": 82, "account_id": "6472380435", "job_id": 1024, "spend": 1976480000, "video_view_25p": 4206, "clicks": 3797, "video_view_75p": 3073, "campaign_id": "11765801249", "video_view_50p": 4470}, {"date": "2021-12-02 00:00:00+00:00", "conversions": 8.417757106873013, "ingestion_time": "2021-12-02T12:06:40.737Z", "channel": "GOOGLE", "agency_id": 79, "impressions": 2484, "line_id": "113891829773", "creative_id": "483794209624", "video_view_complete": 9565, "advertiser_id": 82, "account_id": "6472380435", "job_id": 1024, "spend": 1976480000, "video_view_25p": 3663, "clicks": 9057, "video_view_75p": 1975, "campaign_id": "11765801249", "video_view_50p": 4750}, {"date": "2021-12-02 00:00:00+00:00", "conversions": 21.40435499018024, "ingestion_time": "2021-12-02T12:06:40.737Z", "channel": "GOOGLE", "agency_id": 79, "impressions": 8936, "line_id": "127284931385", "creative_id": "549225733883", "video_view_complete": 9191, "advertiser_id": 82, "account_id": "6472380435", "job_id": 1024, "spend": 1976480000, "video_view_25p": 7371, "clicks": 5211, "video_view_75p": 8733, "campaign_id": "14823424775", "video_view_50p": 9523}, {"date": "2021-12-02 00:00:00+00:00", "conversions": 26.45474367713342, "ingestion_time": "2021-12-02T12:06:40.737Z", "channel": "GOOGLE", "agency_id": 79, "impressions": 5284, "line_id": "127284931385", "creative_id": "549225733883", "video_view_complete": 8490, "advertiser_id": 82, "account_id": "6472380435", "job_id": 1024, "spend": 1976480000, "video_view_25p": 7776, "clicks": 8034, "video_view_75p": 5813, "campaign_id": "14823424775", "video_view_50p": 1692}, {"date": "2021-12-02 00:00:00+00:00", "conversions": 56.56182103154863, "ingestion_time": "2021-12-02T12:06:40.737Z", "channel": "GOOGLE", "agency_id": 79, "impressions": 3021, "line_id": "127649136469", "creative_id": "550546565026", "video_view_complete": 749, "advertiser_id": 82, "account_id": "6472380435", "job_id": 1024, "spend": 1976480000, "video_view_25p": 422, "clicks": 1138, "video_view_75p": 7667, "campaign_id": "14881489614", "video_view_50p": 4381}, {"date": "2021-12-02 00:00:00+00:00", "conversions": 90.11255114544366, "ingestion_time": "2021-12-02T12:06:40.737Z", "channel": "GOOGLE", "agency_id": 79, "impressions": 805, "line_id": "127649136469", "creative_id": "550546565026", "video_view_complete": 3163, "advertiser_id": 82, "account_id": "6472380435", "job_id": 1024, "spend": 1976480000, "video_view_25p": 5363, "clicks": 1965, "video_view_75p": 4306, "campaign_id": "14881489614", "video_view_50p": 5278}, {"date": "2021-12-02 00:00:00+00:00", "conversions": 40.0173762048353, "ingestion_time": "2021-12-02T12:06:40.737Z", "channel": "GOOGLE", "agency_id": 79, "impressions": 6423, "line_id": "127284931385", "creative_id": "549225733886", "video_view_complete": 6055, "advertiser_id": 82, "account_id": "6472380435", "job_id": 1024, "spend": 1976480000, "video_view_25p": 3463, "clicks": 5205, "video_view_75p": 4985, "campaign_id": "14823424775", "video_view_50p": 6749}, {"date": "2021-12-02 00:00:00+00:00", "conversions": 45.86778034810618, "ingestion_time": "2021-12-02T12:06:40.737Z", "channel": "GOOGLE", "agency_id": 79, "impressions": 2870, "line_id": "127284931385", "creative_id": "549225733886", "video_view_complete": 2582, "advertiser_id": 82, "account_id": "6472380435", "job_id": 1024, "spend": 1976480000, "video_view_25p": 9781, "clicks": 8964, "video_view_75p": 7274, "campaign_id": "14823424775", "video_view_50p": 6544}, {"date": "2021-12-02 00:00:00+00:00", "conversions": 16.387590323564048, "ingestion_time": "2021-12-02T12:06:40.737Z", "channel": "GOOGLE", "agency_id": 79, "impressions": 8960, "line_id": "127284931385", "creative_id": "549225733877", "video_view_complete": 7910, "advertiser_id": 82, "account_id": "6472380435", "job_id": 1024, "spend": 1976480000, "video_view_25p": 2782, "clicks": 7888, "video_view_75p": 1107, "campaign_id": "14823424775", "video_view_50p": 8685}, {"date": "2021-12-02 00:00:00+00:00", "conversions": 99.38370696739001, "ingestion_time": "2021-12-02T12:06:40.737Z", "channel": "GOOGLE", "agency_id": 79, "impressions": 7198, "line_id": "127284931385", "creative_id": "549225733877", "video_view_complete": 1758, "advertiser_id": 82, "account_id": "6472380435", "job_id": 1024, "spend": 1976480000, "video_view_25p": 3651, "clicks": 7032, "video_view_75p": 8933, "campaign_id": "14823424775", "video_view_50p": 2893}, {"date": "2021-12-02 00:00:00+00:00", "conversions": 89.87876795515236, "ingestion_time": "2021-12-02T12:06:40.737Z", "channel": "FACEBOOK", "agency_id": 79, "impressions": 6416, "line_id": "23849725967160369", "creative_id": "23849725967310369", "video_view_complete": 783, "advertiser_id": 82, "account_id": "act_903970073442940", "job_id": 1024, "spend": 1976480000, "video_view_25p": 2207, "clicks": 2265, "video_view_75p": 7273, "campaign_id": "23849725966810369", "video_view_50p": 6416}, {"date": "2021-12-02 00:00:00+00:00", "conversions": 75.37798555175812, "ingestion_time": "2021-12-02T12:06:40.737Z", "channel": "FACEBOOK", "agency_id": 79, "impressions": 300, "line_id": "23849725967160369", "creative_id": "23849725967310369", "video_view_complete": 9549, "advertiser_id": 82, "account_id": "act_903970073442940", "job_id": 1024, "spend": 1976480000, "video_view_25p": 1639, "clicks": 7319, "video_view_75p": 5534, "campaign_id": "23849725966810369", "video_view_50p": 1966}, {"date": "2021-12-02 00:00:00+00:00", "conversions": 95.97591012619878, "ingestion_time": "2021-12-02T12:06:40.737Z", "channel": "FACEBOOK", "agency_id": 79, "impressions": 2420, "line_id": "23846437463260369", "creative_id": "23846437463280369", "video_view_complete": 9329, "advertiser_id": 82, "account_id": "act_903970073442940", "job_id": 1024, "spend": 1976480000, "video_view_25p": 5105, "clicks": 9758, "video_view_75p": 2798, "campaign_id": "23846437463240369", "video_view_50p": 5693}, {"date": "2021-12-02 00:00:00+00:00", "conversions": 52.48835343891744, "ingestion_time": "2021-12-02T12:06:40.737Z", "channel": "FACEBOOK", "agency_id": 79, "impressions": 5163, "line_id": "23846437463260369", "creative_id": "23846437463280369", "video_view_complete": 7996, "advertiser_id": 82, "account_id": "act_903970073442940", "job_id": 1024, "spend": 1976480000, "video_view_25p": 9564, "clicks": 9821, "video_view_75p": 3971, "campaign_id": "23846437463240369", "video_view_50p": 7001}, {"date": "2021-12-02 00:00:00+00:00", "conversions": 53.936411634370295, "ingestion_time": "2021-12-02T12:06:40.737Z", "channel": "FACEBOOK", "agency_id": 79, "impressions": 2568, "line_id": "23849765193950369", "creative_id": "23849765194020369", "video_view_complete": 8978, "advertiser_id": 82, "account_id": "act_903970073442940", "job_id": 1024, "spend": 1976480000, "video_view_25p": 3707, "clicks": 8120, "video_view_75p": 4425, "campaign_id": "23849765193560369", "video_view_50p": 9454}, {"date": "2021-12-02 00:00:00+00:00", "conversions": 47.24040263019042, "ingestion_time": "2021-12-02T12:06:40.737Z", "channel": "FACEBOOK", "agency_id": 79, "impressions": 5364, "line_id": "23849765193950369", "creative_id": "23849765194020369", "video_view_complete": 8444, "advertiser_id": 82, "account_id": "act_903970073442940", "job_id": 1024, "spend": 1976480000, "video_view_25p": 3308, "clicks": 9357, "video_view_75p": 4153, "campaign_id": "23849765193560369", "video_view_50p": 8911}, {"date": "2021-12-02 00:00:00+00:00", "conversions": 10.762443258062525, "ingestion_time": "2021-12-02T12:06:40.737Z", "channel": "FACEBOOK", "agency_id": 79, "impressions": 7247, "line_id": "23845998298820213", "creative_id": "23845998784140213", "video_view_complete": 8527, "advertiser_id": 82, "account_id": "act_3427969697428048", "job_id": 1024, "spend": 1976480000, "video_view_25p": 6593, "clicks": 3414, "video_view_75p": 2398, "campaign_id": "23845998298760213", "video_view_50p": 8674}, {"date": "2021-12-02 00:00:00+00:00", "conversions": 89.37781226105663, "ingestion_time": "2021-12-02T12:06:40.737Z", "channel": "FACEBOOK", "agency_id": 79, "impressions": 8835, "line_id": "23845998298820213", "creative_id": "23845998784140213", "video_view_complete": 6548, "advertiser_id": 82, "account_id": "act_3427969697428048", "job_id": 1024, "spend": 1976480000, "video_view_25p": 5466, "clicks": 6096, "video_view_75p": 424, "campaign_id": "23845998298760213", "video_view_50p": 7835}, {"date": "2021-12-02 00:00:00+00:00", "conversions": 94.01754424434844, "ingestion_time": "2021-12-02T12:06:40.737Z", "channel": "FACEBOOK", "agency_id": 79, "impressions": 4984, "line_id": "23849783566440369", "creative_id": "23849783566450369", "video_view_complete": 6694, "advertiser_id": 82, "account_id": "act_903970073442940", "job_id": 1024, "spend": 1976480000, "video_view_25p": 2149, "clicks": 135, "video_view_75p": 8061, "campaign_id": "23849783518160369", "video_view_50p": 290}, {"date": "2021-12-02 00:00:00+00:00", "conversions": 54.64035232208404, "ingestion_time": "2021-12-02T12:06:40.737Z", "channel": "FACEBOOK", "agency_id": 79, "impressions": 2339, "line_id": "23849783566440369", "creative_id": "23849783566450369", "video_view_complete": 2413, "advertiser_id": 82, "account_id": "act_903970073442940", "job_id": 1024, "spend": 1976480000, "video_view_25p": 7011, "clicks": 4394, "video_view_75p": 8859, "campaign_id": "23849783518160369", "video_view_50p": 2447}, {"date": "2021-12-02 00:00:00+00:00", "conversions": 78.62501040357358, "ingestion_time": "2021-12-02T12:06:40.737Z", "channel": "FACEBOOK", "agency_id": 79, "impressions": 8144, "line_id": "23845998298820213", "creative_id": "23845998298890213", "video_view_complete": 4536, "advertiser_id": 82, "account_id": "act_3427969697428048", "job_id": 1024, "spend": 1976480000, "video_view_25p": 6142, "clicks": 5690, "video_view_75p": 4631, "campaign_id": "23845998298760213", "video_view_50p": 7239}, {"date": "2021-12-02 00:00:00+00:00", "conversions": 21.567111266361938, "ingestion_time": "2021-12-02T12:06:40.737Z", "channel": "FACEBOOK", "agency_id": 79, "impressions": 1798, "line_id": "23845998298820213", "creative_id": "23845998298890213", "video_view_complete": 6371, "advertiser_id": 82, "account_id": "act_3427969697428048", "job_id": 1024, "spend": 1976480000, "video_view_25p": 6447, "clicks": 3575, "video_view_75p": 5098, "campaign_id": "23845998298760213", "video_view_50p": 8201}, {"date": "2021-12-03 00:00:00+00:00", "conversions": 34.56966036089006, "ingestion_time": "2021-12-02T12:06:40.737Z", "channel": "GOOGLE", "agency_id": 79, "impressions": 2480, "line_id": "113891829773", "creative_id": "483794209624", "video_view_complete": 4304, "advertiser_id": 82, "account_id": "6472380435", "job_id": 1024, "spend": 1976480000, "video_view_25p": 23, "clicks": 2591, "video_view_75p": 9021, "campaign_id": "11765801249", "video_view_50p": 2759}, {"date": "2021-12-03 00:00:00+00:00", "conversions": 93.82830115364051, "ingestion_time": "2021-12-02T12:06:40.737Z", "channel": "GOOGLE", "agency_id": 79, "impressions": 2562, "line_id": "113891829773", "creative_id": "483794209624", "video_view_complete": 7323, "advertiser_id": 82, "account_id": "6472380435", "job_id": 1024, "spend": 1976480000, "video_view_25p": 2699, "clicks": 8216, "video_view_75p": 3917, "campaign_id": "11765801249", "video_view_50p": 3888}, {"date": "2021-12-03 00:00:00+00:00", "conversions": 98.66473240976043, "ingestion_time": "2021-12-02T12:06:40.737Z", "channel": "GOOGLE", "agency_id": 79, "impressions": 2756, "line_id": "127284931385", "creative_id": "549225733883", "video_view_complete": 6045, "advertiser_id": 82, "account_id": "6472380435", "job_id": 1024, "spend": 1976480000, "video_view_25p": 7559, "clicks": 6458, "video_view_75p": 2025, "campaign_id": "14823424775", "video_view_50p": 3499}, {"date": "2021-12-03 00:00:00+00:00", "conversions": 43.696123097364605, "ingestion_time": "2021-12-02T12:06:40.737Z", "channel": "GOOGLE", "agency_id": 79, "impressions": 1122, "line_id": "127284931385", "creative_id": "549225733883", "video_view_complete": 8631, "advertiser_id": 82, "account_id": "6472380435", "job_id": 1024, "spend": 1976480000, "video_view_25p": 3347, "clicks": 162, "video_view_75p": 2358, "campaign_id": "14823424775", "video_view_50p": 9809}, {"date": "2021-12-03 00:00:00+00:00", "conversions": 97.76717843598442, "ingestion_time": "2021-12-02T12:06:40.737Z", "channel": "GOOGLE", "agency_id": 79, "impressions": 7266, "line_id": "127649136469", "creative_id": "550546565026", "video_view_complete": 1864, "advertiser_id": 82, "account_id": "6472380435", "job_id": 1024, "spend": 1976480000, "video_view_25p": 7513, "clicks": 5097, "video_view_75p": 1154, "campaign_id": "14881489614", "video_view_50p": 7167}, {"date": "2021-12-03 00:00:00+00:00", "conversions": 1.3285078858600752, "ingestion_time": "2021-12-02T12:06:40.737Z", "channel": "GOOGLE", "agency_id": 79, "impressions": 18, "line_id": "127649136469", "creative_id": "550546565026", "video_view_complete": 5673, "advertiser_id": 82, "account_id": "6472380435", "job_id": 1024, "spend": 1976480000, "video_view_25p": 5929, "clicks": 2094, "video_view_75p": 617, "campaign_id": "14881489614", "video_view_50p": 4745}, {"date": "2021-12-03 00:00:00+00:00", "conversions": 62.13094306349017, "ingestion_time": "2021-12-02T12:06:40.737Z", "channel": "GOOGLE", "agency_id": 79, "impressions": 9668, "line_id": "127284931385", "creative_id": "549225733886", "video_view_complete": 8405, "advertiser_id": 82, "account_id": "6472380435", "job_id": 1024, "spend": 1976480000, "video_view_25p": 9366, "clicks": 1040, "video_view_75p": 2361, "campaign_id": "14823424775", "video_view_50p": 6113}, {"date": "2021-12-03 00:00:00+00:00", "conversions": 44.84915522766519, "ingestion_time": "2021-12-02T12:06:40.737Z", "channel": "GOOGLE", "agency_id": 79, "impressions": 7213, "line_id": "127284931385", "creative_id": "549225733886", "video_view_complete": 2630, "advertiser_id": 82, "account_id": "6472380435", "job_id": 1024, "spend": 1976480000, "video_view_25p": 4007, "clicks": 6203, "video_view_75p": 317, "campaign_id": "14823424775", "video_view_50p": 8581}, {"date": "2021-12-03 00:00:00+00:00", "conversions": 39.52218527816994, "ingestion_time": "2021-12-02T12:06:40.737Z", "channel": "GOOGLE", "agency_id": 79, "impressions": 2783, "line_id": "127284931385", "creative_id": "549225733877", "video_view_complete": 8956, "advertiser_id": 82, "account_id": "6472380435", "job_id": 1024, "spend": 1976480000, "video_view_25p": 8312, "clicks": 4108, "video_view_75p": 105, "campaign_id": "14823424775", "video_view_50p": 4862}, {"date": "2021-12-03 00:00:00+00:00", "conversions": 5.935891645649893, "ingestion_time": "2021-12-02T12:06:40.737Z", "channel": "GOOGLE", "agency_id": 79, "impressions": 2375, "line_id": "127284931385", "creative_id": "549225733877", "video_view_complete": 8630, "advertiser_id": 82, "account_id": "6472380435", "job_id": 1024, "spend": 1976480000, "video_view_25p": 5256, "clicks": 7652, "video_view_75p": 9558, "campaign_id": "14823424775", "video_view_50p": 3479}, {"date": "2021-12-03 00:00:00+00:00", "conversions": 99.77042317828577, "ingestion_time": "2021-12-02T12:06:40.737Z", "channel": "FACEBOOK", "agency_id": 79, "impressions": 7995, "line_id": "23849725967160369", "creative_id": "23849725967310369", "video_view_complete": 487, "advertiser_id": 82, "account_id": "act_903970073442940", "job_id": 1024, "spend": 1976480000, "video_view_25p": 705, "clicks": 9165, "video_view_75p": 3415, "campaign_id": "23849725966810369", "video_view_50p": 327}, {"date": "2021-12-03 00:00:00+00:00", "conversions": 22.56512366887533, "ingestion_time": "2021-12-02T12:06:40.737Z", "channel": "FACEBOOK", "agency_id": 79, "impressions": 2080, "line_id": "23849725967160369", "creative_id": "23849725967310369", "video_view_complete": 2987, "advertiser_id": 82, "account_id": "act_903970073442940", "job_id": 1024, "spend": 1976480000, "video_view_25p": 4239, "clicks": 5401, "video_view_75p": 8868, "campaign_id": "23849725966810369", "video_view_50p": 2956}, {"date": "2021-12-03 00:00:00+00:00", "conversions": 71.67676715175908, "ingestion_time": "2021-12-02T12:06:40.737Z", "channel": "FACEBOOK", "agency_id": 79, "impressions": 3350, "line_id": "23846437463260369", "creative_id": "23846437463280369", "video_view_complete": 1469, "advertiser_id": 82, "account_id": "act_903970073442940", "job_id": 1024, "spend": 1976480000, "video_view_25p": 1959, "clicks": 5142, "video_view_75p": 7463, "campaign_id": "23846437463240369", "video_view_50p": 6772}, {"date": "2021-12-03 00:00:00+00:00", "conversions": 96.3870042147018, "ingestion_time": "2021-12-02T12:06:40.737Z", "channel": "FACEBOOK", "agency_id": 79, "impressions": 4712, "line_id": "23846437463260369", "creative_id": "23846437463280369", "video_view_complete": 2761, "advertiser_id": 82, "account_id": "act_903970073442940", "job_id": 1024, "spend": 1976480000, "video_view_25p": 4093, "clicks": 1620, "video_view_75p": 2423, "campaign_id": "23846437463240369", "video_view_50p": 7360}, {"date": "2021-12-03 00:00:00+00:00", "conversions": 1.600671989172131, "ingestion_time": "2021-12-02T12:06:40.737Z", "channel": "FACEBOOK", "agency_id": 79, "impressions": 7471, "line_id": "23849765193950369", "creative_id": "23849765194020369", "video_view_complete": 8262, "advertiser_id": 82, "account_id": "act_903970073442940", "job_id": 1024, "spend": 1976480000, "video_view_25p": 7747, "clicks": 5927, "video_view_75p": 9034, "campaign_id": "23849765193560369", "video_view_50p": 7460}, {"date": "2021-12-03 00:00:00+00:00", "conversions": 14.579739079591302, "ingestion_time": "2021-12-02T12:06:40.737Z", "channel": "FACEBOOK", "agency_id": 79, "impressions": 4920, "line_id": "23849765193950369", "creative_id": "23849765194020369", "video_view_complete": 6564, "advertiser_id": 82, "account_id": "act_903970073442940", "job_id": 1024, "spend": 1976480000, "video_view_25p": 4588, "clicks": 3282, "video_view_75p": 6722, "campaign_id": "23849765193560369", "video_view_50p": 6058}, {"date": "2021-12-03 00:00:00+00:00", "conversions": 20.344210806087514, "ingestion_time": "2021-12-02T12:06:40.737Z", "channel": "FACEBOOK", "agency_id": 79, "impressions": 5206, "line_id": "23845998298820213", "creative_id": "23845998784140213", "video_view_complete": 9239, "advertiser_id": 82, "account_id": "act_3427969697428048", "job_id": 1024, "spend": 1976480000, "video_view_25p": 5033, "clicks": 8569, "video_view_75p": 783, "campaign_id": "23845998298760213", "video_view_50p": 8245}, {"date": "2021-12-03 00:00:00+00:00", "conversions": 6.165146964577883, "ingestion_time": "2021-12-02T12:06:40.737Z", "channel": "FACEBOOK", "agency_id": 79, "impressions": 4331, "line_id": "23845998298820213", "creative_id": "23845998784140213", "video_view_complete": 8191, "advertiser_id": 82, "account_id": "act_3427969697428048", "job_id": 1024, "spend": 1976480000, "video_view_25p": 9991, "clicks": 9654, "video_view_75p": 354, "campaign_id": "23845998298760213", "video_view_50p": 2197}, {"date": "2021-12-03 00:00:00+00:00", "conversions": 17.653455716645972, "ingestion_time": "2021-12-02T12:06:40.737Z", "channel": "FACEBOOK", "agency_id": 79, "impressions": 3195, "line_id": "23849783566440369", "creative_id": "23849783566450369", "video_view_complete": 4562, "advertiser_id": 82, "account_id": "act_903970073442940", "job_id": 1024, "spend": 1976480000, "video_view_25p": 4789, "clicks": 2866, "video_view_75p": 1100, "campaign_id": "23849783518160369", "video_view_50p": 8869}, {"date": "2021-12-03 00:00:00+00:00", "conversions": 76.91253986483353, "ingestion_time": "2021-12-02T12:06:40.737Z", "channel": "FACEBOOK", "agency_id": 79, "impressions": 5357, "line_id": "23849783566440369", "creative_id": "23849783566450369", "video_view_complete": 6956, "advertiser_id": 82, "account_id": "act_903970073442940", "job_id": 1024, "spend": 1976480000, "video_view_25p": 6603, "clicks": 8759, "video_view_75p": 122, "campaign_id": "23849783518160369", "video_view_50p": 2612}, {"date": "2021-12-03 00:00:00+00:00", "conversions": 82.33856785545467, "ingestion_time": "2021-12-02T12:06:40.737Z", "channel": "FACEBOOK", "agency_id": 79, "impressions": 2216, "line_id": "23845998298820213", "creative_id": "23845998298890213", "video_view_complete": 1448, "advertiser_id": 82, "account_id": "act_3427969697428048", "job_id": 1024, "spend": 1976480000, "video_view_25p": 3599, "clicks": 5850, "video_view_75p": 8681, "campaign_id": "23845998298760213", "video_view_50p": 752}, {"date": "2021-12-03 00:00:00+00:00", "conversions": 28.011410895440424, "ingestion_time": "2021-12-02T12:06:40.737Z", "channel": "FACEBOOK", "agency_id": 79, "impressions": 7790, "line_id": "23845998298820213", "creative_id": "23845998298890213", "video_view_complete": 5709, "advertiser_id": 82, "account_id": "act_3427969697428048", "job_id": 1024, "spend": 1976480000, "video_view_25p": 7596, "clicks": 2929, "video_view_75p": 5758, "campaign_id": "23845998298760213", "video_view_50p": 5968}, {"date": "2021-12-04 00:00:00+00:00", "conversions": 72.86768771561827, "ingestion_time": "2021-12-02T12:06:40.737Z", "channel": "GOOGLE", "agency_id": 79, "impressions": 6869, "line_id": "113891829773", "creative_id": "483794209624", "video_view_complete": 1728, "advertiser_id": 82, "account_id": "6472380435", "job_id": 1024, "spend": 1976480000, "video_view_25p": 8236, "clicks": 3554, "video_view_75p": 136, "campaign_id": "11765801249", "video_view_50p": 9085}, {"date": "2021-12-04 00:00:00+00:00", "conversions": 45.25440945636346, "ingestion_time": "2021-12-02T12:06:40.737Z", "channel": "GOOGLE", "agency_id": 79, "impressions": 3984, "line_id": "113891829773", "creative_id": "483794209624", "video_view_complete": 8241, "advertiser_id": 82, "account_id": "6472380435", "job_id": 1024, "spend": 1976480000, "video_view_25p": 4213, "clicks": 5029, "video_view_75p": 3159, "campaign_id": "11765801249", "video_view_50p": 995}, {"date": "2021-12-04 00:00:00+00:00", "conversions": 92.1449820055321, "ingestion_time": "2021-12-02T12:06:40.737Z", "channel": "GOOGLE", "agency_id": 79, "impressions": 8798, "line_id": "127284931385", "creative_id": "549225733883", "video_view_complete": 9721, "advertiser_id": 82, "account_id": "6472380435", "job_id": 1024, "spend": 1976480000, "video_view_25p": 3008, "clicks": 6058, "video_view_75p": 2324, "campaign_id": "14823424775", "video_view_50p": 9797}, {"date": "2021-12-04 00:00:00+00:00", "conversions": 22.48506105632514, "ingestion_time": "2021-12-02T12:06:40.737Z", "channel": "GOOGLE", "agency_id": 79, "impressions": 6453, "line_id": "127284931385", "creative_id": "549225733883", "video_view_complete": 3775, "advertiser_id": 82, "account_id": "6472380435", "job_id": 1024, "spend": 1976480000, "video_view_25p": 6016, "clicks": 2670, "video_view_75p": 908, "campaign_id": "14823424775", "video_view_50p": 9009}, {"date": "2021-12-04 00:00:00+00:00", "conversions": 30.827917078663567, "ingestion_time": "2021-12-02T12:06:40.737Z", "channel": "GOOGLE", "agency_id": 79, "impressions": 9062, "line_id": "127649136469", "creative_id": "550546565026", "video_view_complete": 7181, "advertiser_id": 82, "account_id": "6472380435", "job_id": 1024, "spend": 1976480000, "video_view_25p": 2391, "clicks": 1700, "video_view_75p": 4483, "campaign_id": "14881489614", "video_view_50p": 3109}, {"date": "2021-12-04 00:00:00+00:00", "conversions": 83.84586954060043, "ingestion_time": "2021-12-02T12:06:40.737Z", "channel": "GOOGLE", "agency_id": 79, "impressions": 6798, "line_id": "127649136469", "creative_id": "550546565026", "video_view_complete": 5468, "advertiser_id": 82, "account_id": "6472380435", "job_id": 1024, "spend": 1976480000, "video_view_25p": 1683, "clicks": 1091, "video_view_75p": 9624, "campaign_id": "14881489614", "video_view_50p": 5256}, {"date": "2021-12-04 00:00:00+00:00", "conversions": 18.323646899350976, "ingestion_time": "2021-12-02T12:06:40.737Z", "channel": "GOOGLE", "agency_id": 79, "impressions": 9282, "line_id": "127284931385", "creative_id": "549225733886", "video_view_complete": 5127, "advertiser_id": 82, "account_id": "6472380435", "job_id": 1024, "spend": 1976480000, "video_view_25p": 9831, "clicks": 509, "video_view_75p": 330, "campaign_id": "14823424775", "video_view_50p": 5991}, {"date": "2021-12-04 00:00:00+00:00", "conversions": 64.94762380503037, "ingestion_time": "2021-12-02T12:06:40.737Z", "channel": "GOOGLE", "agency_id": 79, "impressions": 9137, "line_id": "127284931385", "creative_id": "549225733886", "video_view_complete": 1503, "advertiser_id": 82, "account_id": "6472380435", "job_id": 1024, "spend": 1976480000, "video_view_25p": 8559, "clicks": 7898, "video_view_75p": 1892, "campaign_id": "14823424775", "video_view_50p": 4222}, {"date": "2021-12-04 00:00:00+00:00", "conversions": 4.434471596628386, "ingestion_time": "2021-12-02T12:06:40.737Z", "channel": "GOOGLE", "agency_id": 79, "impressions": 3426, "line_id": "127284931385", "creative_id": "549225733877", "video_view_complete": 4864, "advertiser_id": 82, "account_id": "6472380435", "job_id": 1024, "spend": 1976480000, "video_view_25p": 4345, "clicks": 7477, "video_view_75p": 7840, "campaign_id": "14823424775", "video_view_50p": 54}, {"date": "2021-12-04 00:00:00+00:00", "conversions": 85.8165022464752, "ingestion_time": "2021-12-02T12:06:40.737Z", "channel": "GOOGLE", "agency_id": 79, "impressions": 3099, "line_id": "127284931385", "creative_id": "549225733877", "video_view_complete": 3903, "advertiser_id": 82, "account_id": "6472380435", "job_id": 1024, "spend": 1976480000, "video_view_25p": 7227, "clicks": 2403, "video_view_75p": 5878, "campaign_id": "14823424775", "video_view_50p": 6175}, {"date": "2021-12-04 00:00:00+00:00", "conversions": 46.34221635332542, "ingestion_time": "2021-12-02T12:06:40.737Z", "channel": "FACEBOOK", "agency_id": 79, "impressions": 5357, "line_id": "23849725967160369", "creative_id": "23849725967310369", "video_view_complete": 8856, "advertiser_id": 82, "account_id": "act_903970073442940", "job_id": 1024, "spend": 1976480000, "video_view_25p": 4194, "clicks": 7848, "video_view_75p": 291, "campaign_id": "23849725966810369", "video_view_50p": 9466}, {"date": "2021-12-04 00:00:00+00:00", "conversions": 87.48576475726286, "ingestion_time": "2021-12-02T12:06:40.737Z", "channel": "FACEBOOK", "agency_id": 79, "impressions": 6749, "line_id": "23849725967160369", "creative_id": "23849725967310369", "video_view_complete": 3171, "advertiser_id": 82, "account_id": "act_903970073442940", "job_id": 1024, "spend": 1976480000, "video_view_25p": 4361, "clicks": 6162, "video_view_75p": 681, "campaign_id": "23849725966810369", "video_view_50p": 9802}, {"date": "2021-12-04 00:00:00+00:00", "conversions": 48.45932556152918, "ingestion_time": "2021-12-02T12:06:40.737Z", "channel": "FACEBOOK", "agency_id": 79, "impressions": 307, "line_id": "23846437463260369", "creative_id": "23846437463280369", "video_view_complete": 3160, "advertiser_id": 82, "account_id": "act_903970073442940", "job_id": 1024, "spend": 1976480000, "video_view_25p": 9963, "clicks": 1759, "video_view_75p": 9672, "campaign_id": "23846437463240369", "video_view_50p": 7386}, {"date": "2021-12-04 00:00:00+00:00", "conversions": 86.03244778295725, "ingestion_time": "2021-12-02T12:06:40.737Z", "channel": "FACEBOOK", "agency_id": 79, "impressions": 4290, "line_id": "23846437463260369", "creative_id": "23846437463280369", "video_view_complete": 8790, "advertiser_id": 82, "account_id": "act_903970073442940", "job_id": 1024, "spend": 1976480000, "video_view_25p": 99, "clicks": 3686, "video_view_75p": 2399, "campaign_id": "23846437463240369", "video_view_50p": 7455}, {"date": "2021-12-04 00:00:00+00:00", "conversions": 47.44781747097954, "ingestion_time": "2021-12-02T12:06:40.737Z", "channel": "FACEBOOK", "agency_id": 79, "impressions": 2964, "line_id": "23849765193950369", "creative_id": "23849765194020369", "video_view_complete": 1723, "advertiser_id": 82, "account_id": "act_903970073442940", "job_id": 1024, "spend": 1976480000, "video_view_25p": 9667, "clicks": 9063, "video_view_75p": 4229, "campaign_id": "23849765193560369", "video_view_50p": 2347}, {"date": "2021-12-04 00:00:00+00:00", "conversions": 53.06218807095251, "ingestion_time": "2021-12-02T12:06:40.737Z", "channel": "FACEBOOK", "agency_id": 79, "impressions": 1444, "line_id": "23849765193950369", "creative_id": "23849765194020369", "video_view_complete": 2587, "advertiser_id": 82, "account_id": "act_903970073442940", "job_id": 1024, "spend": 1976480000, "video_view_25p": 9478, "clicks": 8372, "video_view_75p": 2257, "campaign_id": "23849765193560369", "video_view_50p": 1968}, {"date": "2021-12-04 00:00:00+00:00", "conversions": 89.48873529762105, "ingestion_time": "2021-12-02T12:06:40.737Z", "channel": "FACEBOOK", "agency_id": 79, "impressions": 5310, "line_id": "23845998298820213", "creative_id": "23845998784140213", "video_view_complete": 1177, "advertiser_id": 82, "account_id": "act_3427969697428048", "job_id": 1024, "spend": 1976480000, "video_view_25p": 6861, "clicks": 378, "video_view_75p": 7903, "campaign_id": "23845998298760213", "video_view_50p": 8120}, {"date": "2021-12-04 00:00:00+00:00", "conversions": 89.26668243537702, "ingestion_time": "2021-12-02T12:06:40.737Z", "channel": "FACEBOOK", "agency_id": 79, "impressions": 8659, "line_id": "23845998298820213", "creative_id": "23845998784140213", "video_view_complete": 9943, "advertiser_id": 82, "account_id": "act_3427969697428048", "job_id": 1024, "spend": 1976480000, "video_view_25p": 4537, "clicks": 7798, "video_view_75p": 1537, "campaign_id": "23845998298760213", "video_view_50p": 6344}, {"date": "2021-12-04 00:00:00+00:00", "conversions": 78.51724562380873, "ingestion_time": "2021-12-02T12:06:40.737Z", "channel": "FACEBOOK", "agency_id": 79, "impressions": 2383, "line_id": "23849783566440369", "creative_id": "23849783566450369", "video_view_complete": 7648, "advertiser_id": 82, "account_id": "act_903970073442940", "job_id": 1024, "spend": 1976480000, "video_view_25p": 2047, "clicks": 5512, "video_view_75p": 4365, "campaign_id": "23849783518160369", "video_view_50p": 3844}, {"date": "2021-12-04 00:00:00+00:00", "conversions": 32.88321077262242, "ingestion_time": "2021-12-02T12:06:40.737Z", "channel": "FACEBOOK", "agency_id": 79, "impressions": 8466, "line_id": "23849783566440369", "creative_id": "23849783566450369", "video_view_complete": 2945, "advertiser_id": 82, "account_id": "act_903970073442940", "job_id": 1024, "spend": 1976480000, "video_view_25p": 565, "clicks": 6852, "video_view_75p": 1585, "campaign_id": "23849783518160369", "video_view_50p": 2128}, {"date": "2021-12-04 00:00:00+00:00", "conversions": 54.87171522072893, "ingestion_time": "2021-12-02T12:06:40.737Z", "channel": "FACEBOOK", "agency_id": 79, "impressions": 3885, "line_id": "23845998298820213", "creative_id": "23845998298890213", "video_view_complete": 8428, "advertiser_id": 82, "account_id": "act_3427969697428048", "job_id": 1024, "spend": 1976480000, "video_view_25p": 6258, "clicks": 8991, "video_view_75p": 3555, "campaign_id": "23845998298760213", "video_view_50p": 8229}, {"date": "2021-12-04 00:00:00+00:00", "conversions": 10.103381798885657, "ingestion_time": "2021-12-02T12:06:40.737Z", "channel": "FACEBOOK", "agency_id": 79, "impressions": 7140, "line_id": "23845998298820213", "creative_id": "23845998298890213", "video_view_complete": 536, "advertiser_id": 82, "account_id": "act_3427969697428048", "job_id": 1024, "spend": 1976480000, "video_view_25p": 1052, "clicks": 3093, "video_view_75p": 7071, "campaign_id": "23845998298760213", "video_view_50p": 5257}, {"date": "2021-12-05 00:00:00+00:00", "conversions": 8.191360339682452, "ingestion_time": "2021-12-02T12:06:40.737Z", "channel": "GOOGLE", "agency_id": 79, "impressions": 4391, "line_id": "113891829773", "creative_id": "483794209624", "video_view_complete": 2945, "advertiser_id": 82, "account_id": "6472380435", "job_id": 1024, "spend": 1976480000, "video_view_25p": 5092, "clicks": 7185, "video_view_75p": 7460, "campaign_id": "11765801249", "video_view_50p": 2757}, {"date": "2021-12-05 00:00:00+00:00", "conversions": 49.53656772423687, "ingestion_time": "2021-12-02T12:06:40.737Z", "channel": "GOOGLE", "agency_id": 79, "impressions": 3111, "line_id": "113891829773", "creative_id": "483794209624", "video_view_complete": 5464, "advertiser_id": 82, "account_id": "6472380435", "job_id": 1024, "spend": 1976480000, "video_view_25p": 3146, "clicks": 869, "video_view_75p": 3910, "campaign_id": "11765801249", "video_view_50p": 4926}, {"date": "2021-12-05 00:00:00+00:00", "conversions": 61.54361823298499, "ingestion_time": "2021-12-02T12:06:40.737Z", "channel": "GOOGLE", "agency_id": 79, "impressions": 5945, "line_id": "127284931385", "creative_id": "549225733883", "video_view_complete": 7188, "advertiser_id": 82, "account_id": "6472380435", "job_id": 1024, "spend": 1976480000, "video_view_25p": 1810, "clicks": 8459, "video_view_75p": 9623, "campaign_id": "14823424775", "video_view_50p": 1452}, {"date": "2021-12-05 00:00:00+00:00", "conversions": 59.485805731081285, "ingestion_time": "2021-12-02T12:06:40.737Z", "channel": "GOOGLE", "agency_id": 79, "impressions": 3783, "line_id": "127284931385", "creative_id": "549225733883", "video_view_complete": 2849, "advertiser_id": 82, "account_id": "6472380435", "job_id": 1024, "spend": 1976480000, "video_view_25p": 9110, "clicks": 9212, "video_view_75p": 9197, "campaign_id": "14823424775", "video_view_50p": 958}, {"date": "2021-12-05 00:00:00+00:00", "conversions": 69.71252310296899, "ingestion_time": "2021-12-02T12:06:40.737Z", "channel": "GOOGLE", "agency_id": 79, "impressions": 6550, "line_id": "127649136469", "creative_id": "550546565026", "video_view_complete": 909, "advertiser_id": 82, "account_id": "6472380435", "job_id": 1024, "spend": 1976480000, "video_view_25p": 282, "clicks": 6423, "video_view_75p": 3700, "campaign_id": "14881489614", "video_view_50p": 7848}, {"date": "2021-12-05 00:00:00+00:00", "conversions": 47.196038604347635, "ingestion_time": "2021-12-02T12:06:40.737Z", "channel": "GOOGLE", "agency_id": 79, "impressions": 6046, "line_id": "127649136469", "creative_id": "550546565026", "video_view_complete": 989, "advertiser_id": 82, "account_id": "6472380435", "job_id": 1024, "spend": 1976480000, "video_view_25p": 8285, "clicks": 7764, "video_view_75p": 6311, "campaign_id": "14881489614", "video_view_50p": 7758}, {"date": "2021-12-05 00:00:00+00:00", "conversions": 23.21696975809393, "ingestion_time": "2021-12-02T12:06:40.737Z", "channel": "GOOGLE", "agency_id": 79, "impressions": 9188, "line_id": "127284931385", "creative_id": "549225733886", "video_view_complete": 131, "advertiser_id": 82, "account_id": "6472380435", "job_id": 1024, "spend": 1976480000, "video_view_25p": 1494, "clicks": 2668, "video_view_75p": 1723, "campaign_id": "14823424775", "video_view_50p": 1548}, {"date": "2021-12-05 00:00:00+00:00", "conversions": 36.61683258151436, "ingestion_time": "2021-12-02T12:06:40.737Z", "channel": "GOOGLE", "agency_id": 79, "impressions": 6763, "line_id": "127284931385", "creative_id": "549225733886", "video_view_complete": 9633, "advertiser_id": 82, "account_id": "6472380435", "job_id": 1024, "spend": 1976480000, "video_view_25p": 4241, "clicks": 1606, "video_view_75p": 4745, "campaign_id": "14823424775", "video_view_50p": 662}, {"date": "2021-12-05 00:00:00+00:00", "conversions": 36.51003558706489, "ingestion_time": "2021-12-02T12:06:40.737Z", "channel": "GOOGLE", "agency_id": 79, "impressions": 4875, "line_id": "127284931385", "creative_id": "549225733877", "video_view_complete": 4060, "advertiser_id": 82, "account_id": "6472380435", "job_id": 1024, "spend": 1976480000, "video_view_25p": 5180, "clicks": 3438, "video_view_75p": 1380, "campaign_id": "14823424775", "video_view_50p": 4132}, {"date": "2021-12-05 00:00:00+00:00", "conversions": 24.053342800285506, "ingestion_time": "2021-12-02T12:06:40.737Z", "channel": "GOOGLE", "agency_id": 79, "impressions": 4781, "line_id": "127284931385", "creative_id": "549225733877", "video_view_complete": 1870, "advertiser_id": 82, "account_id": "6472380435", "job_id": 1024, "spend": 1976480000, "video_view_25p": 8126, "clicks": 5624, "video_view_75p": 7240, "campaign_id": "14823424775", "video_view_50p": 9319}, {"date": "2021-12-05 00:00:00+00:00", "conversions": 42.77473843654684, "ingestion_time": "2021-12-02T12:06:40.737Z", "channel": "FACEBOOK", "agency_id": 79, "impressions": 8433, "line_id": "23849725967160369", "creative_id": "23849725967310369", "video_view_complete": 7630, "advertiser_id": 82, "account_id": "act_903970073442940", "job_id": 1024, "spend": 1976480000, "video_view_25p": 4435, "clicks": 7605, "video_view_75p": 649, "campaign_id": "23849725966810369", "video_view_50p": 8992}, {"date": "2021-12-05 00:00:00+00:00", "conversions": 17.959747688419682, "ingestion_time": "2021-12-02T12:06:40.737Z", "channel": "FACEBOOK", "agency_id": 79, "impressions": 4527, "line_id": "23849725967160369", "creative_id": "23849725967310369", "video_view_complete": 3484, "advertiser_id": 82, "account_id": "act_903970073442940", "job_id": 1024, "spend": 1976480000, "video_view_25p": 8364, "clicks": 1470, "video_view_75p": 5739, "campaign_id": "23849725966810369", "video_view_50p": 9494}, {"date": "2021-12-05 00:00:00+00:00", "conversions": 57.44710069666601, "ingestion_time": "2021-12-02T12:06:40.737Z", "channel": "FACEBOOK", "agency_id": 79, "impressions": 2661, "line_id": "23846437463260369", "creative_id": "23846437463280369", "video_view_complete": 8912, "advertiser_id": 82, "account_id": "act_903970073442940", "job_id": 1024, "spend": 1976480000, "video_view_25p": 6903, "clicks": 8544, "video_view_75p": 1278, "campaign_id": "23846437463240369", "video_view_50p": 9046}, {"date": "2021-12-05 00:00:00+00:00", "conversions": 31.846373095967383, "ingestion_time": "2021-12-02T12:06:40.737Z", "channel": "FACEBOOK", "agency_id": 79, "impressions": 4960, "line_id": "23846437463260369", "creative_id": "23846437463280369", "video_view_complete": 3831, "advertiser_id": 82, "account_id": "act_903970073442940", "job_id": 1024, "spend": 1976480000, "video_view_25p": 6829, "clicks": 9370, "video_view_75p": 1334, "campaign_id": "23846437463240369", "video_view_50p": 5577}, {"date": "2021-12-05 00:00:00+00:00", "conversions": 94.33174509102177, "ingestion_time": "2021-12-02T12:06:40.737Z", "channel": "FACEBOOK", "agency_id": 79, "impressions": 6414, "line_id": "23849765193950369", "creative_id": "23849765194020369", "video_view_complete": 706, "advertiser_id": 82, "account_id": "act_903970073442940", "job_id": 1024, "spend": 1976480000, "video_view_25p": 1708, "clicks": 4778, "video_view_75p": 72, "campaign_id": "23849765193560369", "video_view_50p": 9865}, {"date": "2021-12-05 00:00:00+00:00", "conversions": 99.53204560155476, "ingestion_time": "2021-12-02T12:06:40.737Z", "channel": "FACEBOOK", "agency_id": 79, "impressions": 8472, "line_id": "23849765193950369", "creative_id": "23849765194020369", "video_view_complete": 2860, "advertiser_id": 82, "account_id": "act_903970073442940", "job_id": 1024, "spend": 1976480000, "video_view_25p": 1731, "clicks": 5854, "video_view_75p": 2544, "campaign_id": "23849765193560369", "video_view_50p": 7086}, {"date": "2021-12-05 00:00:00+00:00", "conversions": 19.80581709695086, "ingestion_time": "2021-12-02T12:06:40.737Z", "channel": "FACEBOOK", "agency_id": 79, "impressions": 1030, "line_id": "23845998298820213", "creative_id": "23845998784140213", "video_view_complete": 3982, "advertiser_id": 82, "account_id": "act_3427969697428048", "job_id": 1024, "spend": 1976480000, "video_view_25p": 5135, "clicks": 2739, "video_view_75p": 8637, "campaign_id": "23845998298760213", "video_view_50p": 834}, {"date": "2021-12-05 00:00:00+00:00", "conversions": 83.6925427843001, "ingestion_time": "2021-12-02T12:06:40.737Z", "channel": "FACEBOOK", "agency_id": 79, "impressions": 187, "line_id": "23845998298820213", "creative_id": "23845998784140213", "video_view_complete": 8158, "advertiser_id": 82, "account_id": "act_3427969697428048", "job_id": 1024, "spend": 1976480000, "video_view_25p": 7741, "clicks": 9778, "video_view_75p": 7297, "campaign_id": "23845998298760213", "video_view_50p": 5217}, {"date": "2021-12-05 00:00:00+00:00", "conversions": 86.60830440491843, "ingestion_time": "2021-12-02T12:06:40.737Z", "channel": "FACEBOOK", "agency_id": 79, "impressions": 9122, "line_id": "23849783566440369", "creative_id": "23849783566450369", "video_view_complete": 7856, "advertiser_id": 82, "account_id": "act_903970073442940", "job_id": 1024, "spend": 1976480000, "video_view_25p": 3469, "clicks": 2311, "video_view_75p": 6513, "campaign_id": "23849783518160369", "video_view_50p": 6672}, {"date": "2021-12-05 00:00:00+00:00", "conversions": 53.969090370227214, "ingestion_time": "2021-12-02T12:06:40.737Z", "channel": "FACEBOOK", "agency_id": 79, "impressions": 2544, "line_id": "23849783566440369", "creative_id": "23849783566450369", "video_view_complete": 7364, "advertiser_id": 82, "account_id": "act_903970073442940", "job_id": 1024, "spend": 1976480000, "video_view_25p": 83, "clicks": 9336, "video_view_75p": 4555, "campaign_id": "23849783518160369", "video_view_50p": 4593}, {"date": "2021-12-05 00:00:00+00:00", "conversions": 37.32517821017065, "ingestion_time": "2021-12-02T12:06:40.737Z", "channel": "FACEBOOK", "agency_id": 79, "impressions": 6982, "line_id": "23845998298820213", "creative_id": "23845998298890213", "video_view_complete": 8161, "advertiser_id": 82, "account_id": "act_3427969697428048", "job_id": 1024, "spend": 1976480000, "video_view_25p": 6996, "clicks": 89, "video_view_75p": 6655, "campaign_id": "23845998298760213", "video_view_50p": 2369}, {"date": "2021-12-05 00:00:00+00:00", "conversions": 54.72007822670908, "ingestion_time": "2021-12-02T12:06:40.737Z", "channel": "FACEBOOK", "agency_id": 79, "impressions": 6648, "line_id": "23845998298820213", "creative_id": "23845998298890213", "video_view_complete": 3314, "advertiser_id": 82, "account_id": "act_3427969697428048", "job_id": 1024, "spend": 1976480000, "video_view_25p": 9448, "clicks": 1755, "video_view_75p": 7511, "campaign_id": "23845998298760213", "video_view_50p": 4555}, {"date": "2021-12-06 00:00:00+00:00", "conversions": 22.78218297942959, "ingestion_time": "2021-12-02T12:06:40.737Z", "channel": "GOOGLE", "agency_id": 79, "impressions": 1203, "line_id": "113891829773", "creative_id": "483794209624", "video_view_complete": 7697, "advertiser_id": 82, "account_id": "6472380435", "job_id": 1024, "spend": 1976480000, "video_view_25p": 6950, "clicks": 3008, "video_view_75p": 5250, "campaign_id": "11765801249", "video_view_50p": 8531}, {"date": "2021-12-06 00:00:00+00:00", "conversions": 12.527771188055913, "ingestion_time": "2021-12-02T12:06:40.737Z", "channel": "GOOGLE", "agency_id": 79, "impressions": 7823, "line_id": "113891829773", "creative_id": "483794209624", "video_view_complete": 5196, "advertiser_id": 82, "account_id": "6472380435", "job_id": 1024, "spend": 1976480000, "video_view_25p": 6995, "clicks": 6849, "video_view_75p": 6480, "campaign_id": "11765801249", "video_view_50p": 8343}, {"date": "2021-12-06 00:00:00+00:00", "conversions": 27.245888581214793, "ingestion_time": "2021-12-02T12:06:40.737Z", "channel": "GOOGLE", "agency_id": 79, "impressions": 7456, "line_id": "127284931385", "creative_id": "549225733883", "video_view_complete": 3601, "advertiser_id": 82, "account_id": "6472380435", "job_id": 1024, "spend": 1976480000, "video_view_25p": 9638, "clicks": 8732, "video_view_75p": 5696, "campaign_id": "14823424775", "video_view_50p": 2474}, {"date": "2021-12-06 00:00:00+00:00", "conversions": 41.32533769281523, "ingestion_time": "2021-12-02T12:06:40.737Z", "channel": "GOOGLE", "agency_id": 79, "impressions": 3656, "line_id": "127284931385", "creative_id": "549225733883", "video_view_complete": 4415, "advertiser_id": 82, "account_id": "6472380435", "job_id": 1024, "spend": 1976480000, "video_view_25p": 9100, "clicks": 9483, "video_view_75p": 2672, "campaign_id": "14823424775", "video_view_50p": 5990}, {"date": "2021-12-06 00:00:00+00:00", "conversions": 91.7401043169852, "ingestion_time": "2021-12-02T12:06:40.737Z", "channel": "GOOGLE", "agency_id": 79, "impressions": 5199, "line_id": "127649136469", "creative_id": "550546565026", "video_view_complete": 4016, "advertiser_id": 82, "account_id": "6472380435", "job_id": 1024, "spend": 1976480000, "video_view_25p": 6504, "clicks": 6630, "video_view_75p": 4488, "campaign_id": "14881489614", "video_view_50p": 1271}, {"date": "2021-12-06 00:00:00+00:00", "conversions": 85.3501107885258, "ingestion_time": "2021-12-02T12:06:40.737Z", "channel": "GOOGLE", "agency_id": 79, "impressions": 9038, "line_id": "127649136469", "creative_id": "550546565026", "video_view_complete": 3057, "advertiser_id": 82, "account_id": "6472380435", "job_id": 1024, "spend": 1976480000, "video_view_25p": 3270, "clicks": 6038, "video_view_75p": 7451, "campaign_id": "14881489614", "video_view_50p": 9317}, {"date": "2021-12-06 00:00:00+00:00", "conversions": 22.24955164145651, "ingestion_time": "2021-12-02T12:06:40.737Z", "channel": "GOOGLE", "agency_id": 79, "impressions": 4669, "line_id": "127284931385", "creative_id": "549225733886", "video_view_complete": 603, "advertiser_id": 82, "account_id": "6472380435", "job_id": 1024, "spend": 1976480000, "video_view_25p": 5202, "clicks": 444, "video_view_75p": 5586, "campaign_id": "14823424775", "video_view_50p": 9345}, {"date": "2021-12-06 00:00:00+00:00", "conversions": 34.45764978394571, "ingestion_time": "2021-12-02T12:06:40.737Z", "channel": "GOOGLE", "agency_id": 79, "impressions": 3177, "line_id": "127284931385", "creative_id": "549225733886", "video_view_complete": 9024, "advertiser_id": 82, "account_id": "6472380435", "job_id": 1024, "spend": 1976480000, "video_view_25p": 6672, "clicks": 4613, "video_view_75p": 7940, "campaign_id": "14823424775", "video_view_50p": 7468}, {"date": "2021-12-06 00:00:00+00:00", "conversions": 15.179213925865476, "ingestion_time": "2021-12-02T12:06:40.737Z", "channel": "GOOGLE", "agency_id": 79, "impressions": 713, "line_id": "127284931385", "creative_id": "549225733877", "video_view_complete": 2915, "advertiser_id": 82, "account_id": "6472380435", "job_id": 1024, "spend": 1976480000, "video_view_25p": 5527, "clicks": 7189, "video_view_75p": 2645, "campaign_id": "14823424775", "video_view_50p": 1841}, {"date": "2021-12-06 00:00:00+00:00", "conversions": 61.22470082088894, "ingestion_time": "2021-12-02T12:06:40.737Z", "channel": "GOOGLE", "agency_id": 79, "impressions": 2168, "line_id": "127284931385", "creative_id": "549225733877", "video_view_complete": 2200, "advertiser_id": 82, "account_id": "6472380435", "job_id": 1024, "spend": 1976480000, "video_view_25p": 5208, "clicks": 3682, "video_view_75p": 9471, "campaign_id": "14823424775", "video_view_50p": 5221}, {"date": "2021-12-06 00:00:00+00:00", "conversions": 7.632195640400996, "ingestion_time": "2021-12-02T12:06:40.737Z", "channel": "FACEBOOK", "agency_id": 79, "impressions": 970, "line_id": "23849725967160369", "creative_id": "23849725967310369", "video_view_complete": 499, "advertiser_id": 82, "account_id": "act_903970073442940", "job_id": 1024, "spend": 1976480000, "video_view_25p": 1064, "clicks": 8023, "video_view_75p": 4449, "campaign_id": "23849725966810369", "video_view_50p": 512}, {"date": "2021-12-06 00:00:00+00:00", "conversions": 11.751373417107358, "ingestion_time": "2021-12-02T12:06:40.737Z", "channel": "FACEBOOK", "agency_id": 79, "impressions": 5756, "line_id": "23849725967160369", "creative_id": "23849725967310369", "video_view_complete": 3698, "advertiser_id": 82, "account_id": "act_903970073442940", "job_id": 1024, "spend": 1976480000, "video_view_25p": 598, "clicks": 5303, "video_view_75p": 8919, "campaign_id": "23849725966810369", "video_view_50p": 5635}, {"date": "2021-12-06 00:00:00+00:00", "conversions": 14.746098011773457, "ingestion_time": "2021-12-02T12:06:40.737Z", "channel": "FACEBOOK", "agency_id": 79, "impressions": 5934, "line_id": "23846437463260369", "creative_id": "23846437463280369", "video_view_complete": 5576, "advertiser_id": 82, "account_id": "act_903970073442940", "job_id": 1024, "spend": 1976480000, "video_view_25p": 9179, "clicks": 8166, "video_view_75p": 2499, "campaign_id": "23846437463240369", "video_view_50p": 2422}, {"date": "2021-12-06 00:00:00+00:00", "conversions": 23.855394865778756, "ingestion_time": "2021-12-02T12:06:40.737Z", "channel": "FACEBOOK", "agency_id": 79, "impressions": 4790, "line_id": "23846437463260369", "creative_id": "23846437463280369", "video_view_complete": 4762, "advertiser_id": 82, "account_id": "act_903970073442940", "job_id": 1024, "spend": 1976480000, "video_view_25p": 1101, "clicks": 9515, "video_view_75p": 4706, "campaign_id": "23846437463240369", "video_view_50p": 5888}, {"date": "2021-12-06 00:00:00+00:00", "conversions": 89.49198055896319, "ingestion_time": "2021-12-02T12:06:40.737Z", "channel": "FACEBOOK", "agency_id": 79, "impressions": 4985, "line_id": "23849765193950369", "creative_id": "23849765194020369", "video_view_complete": 5597, "advertiser_id": 82, "account_id": "act_903970073442940", "job_id": 1024, "spend": 1976480000, "video_view_25p": 4242, "clicks": 1992, "video_view_75p": 6275, "campaign_id": "23849765193560369", "video_view_50p": 3305}, {"date": "2021-12-06 00:00:00+00:00", "conversions": 21.28101459045004, "ingestion_time": "2021-12-02T12:06:40.737Z", "channel": "FACEBOOK", "agency_id": 79, "impressions": 188, "line_id": "23849765193950369", "creative_id": "23849765194020369", "video_view_complete": 1871, "advertiser_id": 82, "account_id": "act_903970073442940", "job_id": 1024, "spend": 1976480000, "video_view_25p": 7783, "clicks": 4942, "video_view_75p": 6099, "campaign_id": "23849765193560369", "video_view_50p": 9469}, {"date": "2021-12-06 00:00:00+00:00", "conversions": 78.42102311981431, "ingestion_time": "2021-12-02T12:06:40.737Z", "channel": "FACEBOOK", "agency_id": 79, "impressions": 6760, "line_id": "23845998298820213", "creative_id": "23845998784140213", "video_view_complete": 2976, "advertiser_id": 82, "account_id": "act_3427969697428048", "job_id": 1024, "spend": 1976480000, "video_view_25p": 2953, "clicks": 9601, "video_view_75p": 1911, "campaign_id": "23845998298760213", "video_view_50p": 6348}, {"date": "2021-12-06 00:00:00+00:00", "conversions": 79.97057570443401, "ingestion_time": "2021-12-02T12:06:40.737Z", "channel": "FACEBOOK", "agency_id": 79, "impressions": 248, "line_id": "23845998298820213", "creative_id": "23845998784140213", "video_view_complete": 4225, "advertiser_id": 82, "account_id": "act_3427969697428048", "job_id": 1024, "spend": 1976480000, "video_view_25p": 3344, "clicks": 5493, "video_view_75p": 9680, "campaign_id": "23845998298760213", "video_view_50p": 3424}, {"date": "2021-12-06 00:00:00+00:00", "conversions": 3.59263432804231, "ingestion_time": "2021-12-02T12:06:40.737Z", "channel": "FACEBOOK", "agency_id": 79, "impressions": 7861, "line_id": "23849783566440369", "creative_id": "23849783566450369", "video_view_complete": 1062, "advertiser_id": 82, "account_id": "act_903970073442940", "job_id": 1024, "spend": 1976480000, "video_view_25p": 5211, "clicks": 58, "video_view_75p": 4557, "campaign_id": "23849783518160369", "video_view_50p": 2125}, {"date": "2021-12-06 00:00:00+00:00", "conversions": 15.849181404661106, "ingestion_time": "2021-12-02T12:06:40.737Z", "channel": "FACEBOOK", "agency_id": 79, "impressions": 8580, "line_id": "23849783566440369", "creative_id": "23849783566450369", "video_view_complete": 7338, "advertiser_id": 82, "account_id": "act_903970073442940", "job_id": 1024, "spend": 1976480000, "video_view_25p": 9787, "clicks": 3535, "video_view_75p": 6228, "campaign_id": "23849783518160369", "video_view_50p": 1116}, {"date": "2021-12-06 00:00:00+00:00", "conversions": 12.491278085453871, "ingestion_time": "2021-12-02T12:06:40.737Z", "channel": "FACEBOOK", "agency_id": 79, "impressions": 5078, "line_id": "23845998298820213", "creative_id": "23845998298890213", "video_view_complete": 8251, "advertiser_id": 82, "account_id": "act_3427969697428048", "job_id": 1024, "spend": 1976480000, "video_view_25p": 6085, "clicks": 1686, "video_view_75p": 6350, "campaign_id": "23845998298760213", "video_view_50p": 4751}, {"date": "2021-12-06 00:00:00+00:00", "conversions": 86.06523643666972, "ingestion_time": "2021-12-02T12:06:40.737Z", "channel": "FACEBOOK", "agency_id": 79, "impressions": 6124, "line_id": "23845998298820213", "creative_id": "23845998298890213", "video_view_complete": 9349, "advertiser_id": 82, "account_id": "act_3427969697428048", "job_id": 1024, "spend": 1976480000, "video_view_25p": 346, "clicks": 2276, "video_view_75p": 4001, "campaign_id": "23845998298760213", "video_view_50p": 6376}, {"date": "2021-12-07 00:00:00+00:00", "conversions": 63.348639239580386, "ingestion_time": "2021-12-02T12:06:40.737Z", "channel": "GOOGLE", "agency_id": 79, "impressions": 5956, "line_id": "113891829773", "creative_id": "483794209624", "video_view_complete": 8952, "advertiser_id": 82, "account_id": "6472380435", "job_id": 1024, "spend": 1976480000, "video_view_25p": 8370, "clicks": 2701, "video_view_75p": 7973, "campaign_id": "11765801249", "video_view_50p": 4231}, {"date": "2021-12-07 00:00:00+00:00", "conversions": 40.834843090790365, "ingestion_time": "2021-12-02T12:06:40.737Z", "channel": "GOOGLE", "agency_id": 79, "impressions": 3019, "line_id": "113891829773", "creative_id": "483794209624", "video_view_complete": 9765, "advertiser_id": 82, "account_id": "6472380435", "job_id": 1024, "spend": 1976480000, "video_view_25p": 6083, "clicks": 9636, "video_view_75p": 5439, "campaign_id": "11765801249", "video_view_50p": 8820}, {"date": "2021-12-07 00:00:00+00:00", "conversions": 55.40178871919916, "ingestion_time": "2021-12-02T12:06:40.737Z", "channel": "GOOGLE", "agency_id": 79, "impressions": 9298, "line_id": "127284931385", "creative_id": "549225733883", "video_view_complete": 7702, "advertiser_id": 82, "account_id": "6472380435", "job_id": 1024, "spend": 1976480000, "video_view_25p": 6416, "clicks": 2749, "video_view_75p": 376, "campaign_id": "14823424775", "video_view_50p": 323}, {"date": "2021-12-07 00:00:00+00:00", "conversions": 30.558880021429125, "ingestion_time": "2021-12-02T12:06:40.737Z", "channel": "GOOGLE", "agency_id": 79, "impressions": 1627, "line_id": "127284931385", "creative_id": "549225733883", "video_view_complete": 4733, "advertiser_id": 82, "account_id": "6472380435", "job_id": 1024, "spend": 1976480000, "video_view_25p": 7319, "clicks": 815, "video_view_75p": 4100, "campaign_id": "14823424775", "video_view_50p": 490}, {"date": "2021-12-07 00:00:00+00:00", "conversions": 74.86028594880304, "ingestion_time": "2021-12-02T12:06:40.737Z", "channel": "GOOGLE", "agency_id": 79, "impressions": 4679, "line_id": "127649136469", "creative_id": "550546565026", "video_view_complete": 9507, "advertiser_id": 82, "account_id": "6472380435", "job_id": 1024, "spend": 1976480000, "video_view_25p": 30, "clicks": 7175, "video_view_75p": 579, "campaign_id": "14881489614", "video_view_50p": 4752}, {"date": "2021-12-07 00:00:00+00:00", "conversions": 59.59755611010019, "ingestion_time": "2021-12-02T12:06:40.737Z", "channel": "GOOGLE", "agency_id": 79, "impressions": 8484, "line_id": "127649136469", "creative_id": "550546565026", "video_view_complete": 9815, "advertiser_id": 82, "account_id": "6472380435", "job_id": 1024, "spend": 1976480000, "video_view_25p": 6177, "clicks": 3780, "video_view_75p": 879, "campaign_id": "14881489614", "video_view_50p": 7191}, {"date": "2021-12-07 00:00:00+00:00", "conversions": 43.535771159671775, "ingestion_time": "2021-12-02T12:06:40.737Z", "channel": "GOOGLE", "agency_id": 79, "impressions": 2885, "line_id": "127284931385", "creative_id": "549225733886", "video_view_complete": 9942, "advertiser_id": 82, "account_id": "6472380435", "job_id": 1024, "spend": 1976480000, "video_view_25p": 8718, "clicks": 4843, "video_view_75p": 4325, "campaign_id": "14823424775", "video_view_50p": 733}, {"date": "2021-12-07 00:00:00+00:00", "conversions": 9.826320547340895, "ingestion_time": "2021-12-02T12:06:40.737Z", "channel": "GOOGLE", "agency_id": 79, "impressions": 9159, "line_id": "127284931385", "creative_id": "549225733886", "video_view_complete": 2573, "advertiser_id": 82, "account_id": "6472380435", "job_id": 1024, "spend": 1976480000, "video_view_25p": 353, "clicks": 3219, "video_view_75p": 167, "campaign_id": "14823424775", "video_view_50p": 8227}, {"date": "2021-12-07 00:00:00+00:00", "conversions": 66.32647885836793, "ingestion_time": "2021-12-02T12:06:40.737Z", "channel": "GOOGLE", "agency_id": 79, "impressions": 2711, "line_id": "127284931385", "creative_id": "549225733877", "video_view_complete": 7821, "advertiser_id": 82, "account_id": "6472380435", "job_id": 1024, "spend": 1976480000, "video_view_25p": 6961, "clicks": 793, "video_view_75p": 9510, "campaign_id": "14823424775", "video_view_50p": 837}, {"date": "2021-12-07 00:00:00+00:00", "conversions": 92.63057002904675, "ingestion_time": "2021-12-02T12:06:40.737Z", "channel": "GOOGLE", "agency_id": 79, "impressions": 7999, "line_id": "127284931385", "creative_id": "549225733877", "video_view_complete": 6837, "advertiser_id": 82, "account_id": "6472380435", "job_id": 1024, "spend": 1976480000, "video_view_25p": 1571, "clicks": 1293, "video_view_75p": 8859, "campaign_id": "14823424775", "video_view_50p": 6183}, {"date": "2021-12-07 00:00:00+00:00", "conversions": 98.31612077678021, "ingestion_time": "2021-12-02T12:06:40.737Z", "channel": "FACEBOOK", "agency_id": 79, "impressions": 6429, "line_id": "23849725967160369", "creative_id": "23849725967310369", "video_view_complete": 5409, "advertiser_id": 82, "account_id": "act_903970073442940", "job_id": 1024, "spend": 1976480000, "video_view_25p": 1849, "clicks": 1928, "video_view_75p": 9213, "campaign_id": "23849725966810369", "video_view_50p": 8720}, {"date": "2021-12-07 00:00:00+00:00", "conversions": 0.2990777317547155, "ingestion_time": "2021-12-02T12:06:40.737Z", "channel": "FACEBOOK", "agency_id": 79, "impressions": 6690, "line_id": "23849725967160369", "creative_id": "23849725967310369", "video_view_complete": 8978, "advertiser_id": 82, "account_id": "act_903970073442940", "job_id": 1024, "spend": 1976480000, "video_view_25p": 7691, "clicks": 7773, "video_view_75p": 5529, "campaign_id": "23849725966810369", "video_view_50p": 2864}, {"date": "2021-12-07 00:00:00+00:00", "conversions": 72.16848275841201, "ingestion_time": "2021-12-02T12:06:40.737Z", "channel": "FACEBOOK", "agency_id": 79, "impressions": 7037, "line_id": "23846437463260369", "creative_id": "23846437463280369", "video_view_complete": 773, "advertiser_id": 82, "account_id": "act_903970073442940", "job_id": 1024, "spend": 1976480000, "video_view_25p": 7675, "clicks": 3732, "video_view_75p": 7414, "campaign_id": "23846437463240369", "video_view_50p": 9392}, {"date": "2021-12-07 00:00:00+00:00", "conversions": 62.478279421030805, "ingestion_time": "2021-12-02T12:06:40.737Z", "channel": "FACEBOOK", "agency_id": 79, "impressions": 8911, "line_id": "23846437463260369", "creative_id": "23846437463280369", "video_view_complete": 1530, "advertiser_id": 82, "account_id": "act_903970073442940", "job_id": 1024, "spend": 1976480000, "video_view_25p": 2234, "clicks": 9696, "video_view_75p": 4543, "campaign_id": "23846437463240369", "video_view_50p": 3219}, {"date": "2021-12-07 00:00:00+00:00", "conversions": 59.70455832374697, "ingestion_time": "2021-12-02T12:06:40.737Z", "channel": "FACEBOOK", "agency_id": 79, "impressions": 8339, "line_id": "23849765193950369", "creative_id": "23849765194020369", "video_view_complete": 5421, "advertiser_id": 82, "account_id": "act_903970073442940", "job_id": 1024, "spend": 1976480000, "video_view_25p": 378, "clicks": 3554, "video_view_75p": 3797, "campaign_id": "23849765193560369", "video_view_50p": 9131}, {"date": "2021-12-07 00:00:00+00:00", "conversions": 79.10227790579879, "ingestion_time": "2021-12-02T12:06:40.737Z", "channel": "FACEBOOK", "agency_id": 79, "impressions": 9731, "line_id": "23849765193950369", "creative_id": "23849765194020369", "video_view_complete": 3702, "advertiser_id": 82, "account_id": "act_903970073442940", "job_id": 1024, "spend": 1976480000, "video_view_25p": 3519, "clicks": 5689, "video_view_75p": 4747, "campaign_id": "23849765193560369", "video_view_50p": 8278}, {"date": "2021-12-07 00:00:00+00:00", "conversions": 22.618498016639023, "ingestion_time": "2021-12-02T12:06:40.737Z", "channel": "FACEBOOK", "agency_id": 79, "impressions": 4874, "line_id": "23845998298820213", "creative_id": "23845998784140213", "video_view_complete": 3808, "advertiser_id": 82, "account_id": "act_3427969697428048", "job_id": 1024, "spend": 1976480000, "video_view_25p": 1021, "clicks": 4747, "video_view_75p": 9222, "campaign_id": "23845998298760213", "video_view_50p": 6437}, {"date": "2021-12-07 00:00:00+00:00", "conversions": 31.105024467584165, "ingestion_time": "2021-12-02T12:06:40.737Z", "channel": "FACEBOOK", "agency_id": 79, "impressions": 4455, "line_id": "23845998298820213", "creative_id": "23845998784140213", "video_view_complete": 7732, "advertiser_id": 82, "account_id": "act_3427969697428048", "job_id": 1024, "spend": 1976480000, "video_view_25p": 3612, "clicks": 4649, "video_view_75p": 1554, "campaign_id": "23845998298760213", "video_view_50p": 3767}, {"date": "2021-12-07 00:00:00+00:00", "conversions": 89.80489576702016, "ingestion_time": "2021-12-02T12:06:40.737Z", "channel": "FACEBOOK", "agency_id": 79, "impressions": 8736, "line_id": "23849783566440369", "creative_id": "23849783566450369", "video_view_complete": 4529, "advertiser_id": 82, "account_id": "act_903970073442940", "job_id": 1024, "spend": 1976480000, "video_view_25p": 6749, "clicks": 3725, "video_view_75p": 7491, "campaign_id": "23849783518160369", "video_view_50p": 7621}, {"date": "2021-12-07 00:00:00+00:00", "conversions": 33.3049132460341, "ingestion_time": "2021-12-02T12:06:40.737Z", "channel": "FACEBOOK", "agency_id": 79, "impressions": 6488, "line_id": "23849783566440369", "creative_id": "23849783566450369", "video_view_complete": 3079, "advertiser_id": 82, "account_id": "act_903970073442940", "job_id": 1024, "spend": 1976480000, "video_view_25p": 2456, "clicks": 9561, "video_view_75p": 4895, "campaign_id": "23849783518160369", "video_view_50p": 8935}, {"date": "2021-12-07 00:00:00+00:00", "conversions": 24.446008768495208, "ingestion_time": "2021-12-02T12:06:40.737Z", "channel": "FACEBOOK", "agency_id": 79, "impressions": 2484, "line_id": "23845998298820213", "creative_id": "23845998298890213", "video_view_complete": 2383, "advertiser_id": 82, "account_id": "act_3427969697428048", "job_id": 1024, "spend": 1976480000, "video_view_25p": 1555, "clicks": 1487, "video_view_75p": 5207, "campaign_id": "23845998298760213", "video_view_50p": 7840}, {"date": "2021-12-07 00:00:00+00:00", "conversions": 8.459727957359354, "ingestion_time": "2021-12-02T12:06:40.737Z", "channel": "FACEBOOK", "agency_id": 79, "impressions": 2763, "line_id": "23845998298820213", "creative_id": "23845998298890213", "video_view_complete": 3807, "advertiser_id": 82, "account_id": "act_3427969697428048", "job_id": 1024, "spend": 1976480000, "video_view_25p": 2566, "clicks": 1127, "video_view_75p": 5569, "campaign_id": "23845998298760213", "video_view_50p": 7293}, {"date": "2021-12-08 00:00:00+00:00", "conversions": 38.41500532042718, "ingestion_time": "2021-12-02T12:06:40.737Z", "channel": "GOOGLE", "agency_id": 79, "impressions": 4662, "line_id": "113891829773", "creative_id": "483794209624", "video_view_complete": 1055, "advertiser_id": 82, "account_id": "6472380435", "job_id": 1024, "spend": 1976480000, "video_view_25p": 7824, "clicks": 8855, "video_view_75p": 2377, "campaign_id": "11765801249", "video_view_50p": 3366}, {"date": "2021-12-08 00:00:00+00:00", "conversions": 57.03908838725232, "ingestion_time": "2021-12-02T12:06:40.737Z", "channel": "GOOGLE", "agency_id": 79, "impressions": 7595, "line_id": "113891829773", "creative_id": "483794209624", "video_view_complete": 1824, "advertiser_id": 82, "account_id": "6472380435", "job_id": 1024, "spend": 1976480000, "video_view_25p": 7826, "clicks": 3030, "video_view_75p": 5925, "campaign_id": "11765801249", "video_view_50p": 3529}, {"date": "2021-12-08 00:00:00+00:00", "conversions": 39.377980287266425, "ingestion_time": "2021-12-02T12:06:40.737Z", "channel": "GOOGLE", "agency_id": 79, "impressions": 1489, "line_id": "127284931385", "creative_id": "549225733883", "video_view_complete": 2948, "advertiser_id": 82, "account_id": "6472380435", "job_id": 1024, "spend": 1976480000, "video_view_25p": 6541, "clicks": 2448, "video_view_75p": 2508, "campaign_id": "14823424775", "video_view_50p": 4399}, {"date": "2021-12-08 00:00:00+00:00", "conversions": 79.30860173753851, "ingestion_time": "2021-12-02T12:06:40.737Z", "channel": "GOOGLE", "agency_id": 79, "impressions": 1189, "line_id": "127284931385", "creative_id": "549225733883", "video_view_complete": 6498, "advertiser_id": 82, "account_id": "6472380435", "job_id": 1024, "spend": 1976480000, "video_view_25p": 3380, "clicks": 90, "video_view_75p": 3, "campaign_id": "14823424775", "video_view_50p": 6584}, {"date": "2021-12-08 00:00:00+00:00", "conversions": 81.90129328158856, "ingestion_time": "2021-12-02T12:06:40.737Z", "channel": "GOOGLE", "agency_id": 79, "impressions": 5391, "line_id": "127649136469", "creative_id": "550546565026", "video_view_complete": 9063, "advertiser_id": 82, "account_id": "6472380435", "job_id": 1024, "spend": 1976480000, "video_view_25p": 4768, "clicks": 9869, "video_view_75p": 1491, "campaign_id": "14881489614", "video_view_50p": 1748}, {"date": "2021-12-08 00:00:00+00:00", "conversions": 61.30559520409838, "ingestion_time": "2021-12-02T12:06:40.737Z", "channel": "GOOGLE", "agency_id": 79, "impressions": 5703, "line_id": "127649136469", "creative_id": "550546565026", "video_view_complete": 3967, "advertiser_id": 82, "account_id": "6472380435", "job_id": 1024, "spend": 1976480000, "video_view_25p": 4683, "clicks": 458, "video_view_75p": 6868, "campaign_id": "14881489614", "video_view_50p": 1004}, {"date": "2021-12-08 00:00:00+00:00", "conversions": 96.81301094481117, "ingestion_time": "2021-12-02T12:06:40.737Z", "channel": "GOOGLE", "agency_id": 79, "impressions": 6646, "line_id": "127284931385", "creative_id": "549225733886", "video_view_complete": 6639, "advertiser_id": 82, "account_id": "6472380435", "job_id": 1024, "spend": 1976480000, "video_view_25p": 1273, "clicks": 48, "video_view_75p": 339, "campaign_id": "14823424775", "video_view_50p": 5749}, {"date": "2021-12-08 00:00:00+00:00", "conversions": 93.82946597221458, "ingestion_time": "2021-12-02T12:06:40.737Z", "channel": "GOOGLE", "agency_id": 79, "impressions": 4226, "line_id": "127284931385", "creative_id": "549225733886", "video_view_complete": 4345, "advertiser_id": 82, "account_id": "6472380435", "job_id": 1024, "spend": 1976480000, "video_view_25p": 9208, "clicks": 1924, "video_view_75p": 8906, "campaign_id": "14823424775", "video_view_50p": 6482}, {"date": "2021-12-08 00:00:00+00:00", "conversions": 7.199028234237548, "ingestion_time": "2021-12-02T12:06:40.737Z", "channel": "GOOGLE", "agency_id": 79, "impressions": 6884, "line_id": "127284931385", "creative_id": "549225733877", "video_view_complete": 258, "advertiser_id": 82, "account_id": "6472380435", "job_id": 1024, "spend": 1976480000, "video_view_25p": 3641, "clicks": 4095, "video_view_75p": 238, "campaign_id": "14823424775", "video_view_50p": 2653}, {"date": "2021-12-08 00:00:00+00:00", "conversions": 85.66112803005991, "ingestion_time": "2021-12-02T12:06:40.737Z", "channel": "GOOGLE", "agency_id": 79, "impressions": 9255, "line_id": "127284931385", "creative_id": "549225733877", "video_view_complete": 9079, "advertiser_id": 82, "account_id": "6472380435", "job_id": 1024, "spend": 1976480000, "video_view_25p": 3217, "clicks": 1942, "video_view_75p": 2069, "campaign_id": "14823424775", "video_view_50p": 7663}, {"date": "2021-12-08 00:00:00+00:00", "conversions": 39.49034441630263, "ingestion_time": "2021-12-02T12:06:40.737Z", "channel": "FACEBOOK", "agency_id": 79, "impressions": 4235, "line_id": "23849725967160369", "creative_id": "23849725967310369", "video_view_complete": 5792, "advertiser_id": 82, "account_id": "act_903970073442940", "job_id": 1024, "spend": 1976480000, "video_view_25p": 1335, "clicks": 6906, "video_view_75p": 7174, "campaign_id": "23849725966810369", "video_view_50p": 1777}, {"date": "2021-12-08 00:00:00+00:00", "conversions": 26.051878492110237, "ingestion_time": "2021-12-02T12:06:40.737Z", "channel": "FACEBOOK", "agency_id": 79, "impressions": 5105, "line_id": "23849725967160369", "creative_id": "23849725967310369", "video_view_complete": 8410, "advertiser_id": 82, "account_id": "act_903970073442940", "job_id": 1024, "spend": 1976480000, "video_view_25p": 1162, "clicks": 302, "video_view_75p": 3776, "campaign_id": "23849725966810369", "video_view_50p": 6052}, {"date": "2021-12-08 00:00:00+00:00", "conversions": 68.93375645662391, "ingestion_time": "2021-12-02T12:06:40.737Z", "channel": "FACEBOOK", "agency_id": 79, "impressions": 4388, "line_id": "23846437463260369", "creative_id": "23846437463280369", "video_view_complete": 9808, "advertiser_id": 82, "account_id": "act_903970073442940", "job_id": 1024, "spend": 1976480000, "video_view_25p": 7204, "clicks": 642, "video_view_75p": 7064, "campaign_id": "23846437463240369", "video_view_50p": 8280}, {"date": "2021-12-08 00:00:00+00:00", "conversions": 4.353086898622848, "ingestion_time": "2021-12-02T12:06:40.737Z", "channel": "FACEBOOK", "agency_id": 79, "impressions": 1774, "line_id": "23846437463260369", "creative_id": "23846437463280369", "video_view_complete": 6943, "advertiser_id": 82, "account_id": "act_903970073442940", "job_id": 1024, "spend": 1976480000, "video_view_25p": 1405, "clicks": 1050, "video_view_75p": 5520, "campaign_id": "23846437463240369", "video_view_50p": 1932}, {"date": "2021-12-08 00:00:00+00:00", "conversions": 47.432337757517196, "ingestion_time": "2021-12-02T12:06:40.737Z", "channel": "FACEBOOK", "agency_id": 79, "impressions": 1831, "line_id": "23849765193950369", "creative_id": "23849765194020369", "video_view_complete": 7913, "advertiser_id": 82, "account_id": "act_903970073442940", "job_id": 1024, "spend": 1976480000, "video_view_25p": 1768, "clicks": 5645, "video_view_75p": 5736, "campaign_id": "23849765193560369", "video_view_50p": 7906}, {"date": "2021-12-08 00:00:00+00:00", "conversions": 16.914507885291428, "ingestion_time": "2021-12-02T12:06:40.737Z", "channel": "FACEBOOK", "agency_id": 79, "impressions": 2043, "line_id": "23849765193950369", "creative_id": "23849765194020369", "video_view_complete": 963, "advertiser_id": 82, "account_id": "act_903970073442940", "job_id": 1024, "spend": 1976480000, "video_view_25p": 6625, "clicks": 6723, "video_view_75p": 3022, "campaign_id": "23849765193560369", "video_view_50p": 8069}, {"date": "2021-12-08 00:00:00+00:00", "conversions": 52.60677572111173, "ingestion_time": "2021-12-02T12:06:40.737Z", "channel": "FACEBOOK", "agency_id": 79, "impressions": 8767, "line_id": "23845998298820213", "creative_id": "23845998784140213", "video_view_complete": 5072, "advertiser_id": 82, "account_id": "act_3427969697428048", "job_id": 1024, "spend": 1976480000, "video_view_25p": 9325, "clicks": 5908, "video_view_75p": 2573, "campaign_id": "23845998298760213", "video_view_50p": 311}, {"date": "2021-12-08 00:00:00+00:00", "conversions": 77.13228558832256, "ingestion_time": "2021-12-02T12:06:40.737Z", "channel": "FACEBOOK", "agency_id": 79, "impressions": 359, "line_id": "23845998298820213", "creative_id": "23845998784140213", "video_view_complete": 7232, "advertiser_id": 82, "account_id": "act_3427969697428048", "job_id": 1024, "spend": 1976480000, "video_view_25p": 7193, "clicks": 2555, "video_view_75p": 8877, "campaign_id": "23845998298760213", "video_view_50p": 657}, {"date": "2021-12-08 00:00:00+00:00", "conversions": 30.775072126601355, "ingestion_time": "2021-12-02T12:06:40.737Z", "channel": "FACEBOOK", "agency_id": 79, "impressions": 5656, "line_id": "23849783566440369", "creative_id": "23849783566450369", "video_view_complete": 8824, "advertiser_id": 82, "account_id": "act_903970073442940", "job_id": 1024, "spend": 1976480000, "video_view_25p": 1459, "clicks": 8139, "video_view_75p": 2590, "campaign_id": "23849783518160369", "video_view_50p": 7597}, {"date": "2021-12-08 00:00:00+00:00", "conversions": 3.6641366082570626, "ingestion_time": "2021-12-02T12:06:40.737Z", "channel": "FACEBOOK", "agency_id": 79, "impressions": 1472, "line_id": "23849783566440369", "creative_id": "23849783566450369", "video_view_complete": 1923, "advertiser_id": 82, "account_id": "act_903970073442940", "job_id": 1024, "spend": 1976480000, "video_view_25p": 6804, "clicks": 1311, "video_view_75p": 1025, "campaign_id": "23849783518160369", "video_view_50p": 8298}, {"date": "2021-12-08 00:00:00+00:00", "conversions": 99.73241963788591, "ingestion_time": "2021-12-02T12:06:40.737Z", "channel": "FACEBOOK", "agency_id": 79, "impressions": 6364, "line_id": "23845998298820213", "creative_id": "23845998298890213", "video_view_complete": 9020, "advertiser_id": 82, "account_id": "act_3427969697428048", "job_id": 1024, "spend": 1976480000, "video_view_25p": 8966, "clicks": 6577, "video_view_75p": 4829, "campaign_id": "23845998298760213", "video_view_50p": 6726}, {"date": "2021-12-08 00:00:00+00:00", "conversions": 42.46092042005597, "ingestion_time": "2021-12-02T12:06:40.737Z", "channel": "FACEBOOK", "agency_id": 79, "impressions": 7753, "line_id": "23845998298820213", "creative_id": "23845998298890213", "video_view_complete": 8726, "advertiser_id": 82, "account_id": "act_3427969697428048", "job_id": 1024, "spend": 1976480000, "video_view_25p": 9578, "clicks": 7042, "video_view_75p": 7469, "campaign_id": "23845998298760213", "video_view_50p": 380}, {"date": "2021-12-09 00:00:00+00:00", "conversions": 7.364559334472142, "ingestion_time": "2021-12-02T12:06:40.737Z", "channel": "GOOGLE", "agency_id": 79, "impressions": 6263, "line_id": "113891829773", "creative_id": "483794209624", "video_view_complete": 6559, "advertiser_id": 82, "account_id": "6472380435", "job_id": 1024, "spend": 1976480000, "video_view_25p": 1150, "clicks": 9985, "video_view_75p": 3865, "campaign_id": "11765801249", "video_view_50p": 5179}, {"date": "2021-12-09 00:00:00+00:00", "conversions": 38.22881546022644, "ingestion_time": "2021-12-02T12:06:40.737Z", "channel": "GOOGLE", "agency_id": 79, "impressions": 9137, "line_id": "113891829773", "creative_id": "483794209624", "video_view_complete": 7135, "advertiser_id": 82, "account_id": "6472380435", "job_id": 1024, "spend": 1976480000, "video_view_25p": 5890, "clicks": 2442, "video_view_75p": 9752, "campaign_id": "11765801249", "video_view_50p": 5146}, {"date": "2021-12-09 00:00:00+00:00", "conversions": 43.15478765470356, "ingestion_time": "2021-12-02T12:06:40.737Z", "channel": "GOOGLE", "agency_id": 79, "impressions": 9234, "line_id": "127284931385", "creative_id": "549225733883", "video_view_complete": 191, "advertiser_id": 82, "account_id": "6472380435", "job_id": 1024, "spend": 1976480000, "video_view_25p": 1826, "clicks": 4641, "video_view_75p": 163, "campaign_id": "14823424775", "video_view_50p": 737}, {"date": "2021-12-09 00:00:00+00:00", "conversions": 44.503570561448726, "ingestion_time": "2021-12-02T12:06:40.737Z", "channel": "GOOGLE", "agency_id": 79, "impressions": 2471, "line_id": "127284931385", "creative_id": "549225733883", "video_view_complete": 5961, "advertiser_id": 82, "account_id": "6472380435", "job_id": 1024, "spend": 1976480000, "video_view_25p": 6349, "clicks": 2565, "video_view_75p": 4998, "campaign_id": "14823424775", "video_view_50p": 3551}, {"date": "2021-12-09 00:00:00+00:00", "conversions": 11.709513463776355, "ingestion_time": "2021-12-02T12:06:40.737Z", "channel": "GOOGLE", "agency_id": 79, "impressions": 4920, "line_id": "127649136469", "creative_id": "550546565026", "video_view_complete": 3550, "advertiser_id": 82, "account_id": "6472380435", "job_id": 1024, "spend": 1976480000, "video_view_25p": 2493, "clicks": 6990, "video_view_75p": 2974, "campaign_id": "14881489614", "video_view_50p": 8645}, {"date": "2021-12-09 00:00:00+00:00", "conversions": 79.5512611348348, "ingestion_time": "2021-12-02T12:06:40.737Z", "channel": "GOOGLE", "agency_id": 79, "impressions": 4154, "line_id": "127649136469", "creative_id": "550546565026", "video_view_complete": 7622, "advertiser_id": 82, "account_id": "6472380435", "job_id": 1024, "spend": 1976480000, "video_view_25p": 4617, "clicks": 6688, "video_view_75p": 5986, "campaign_id": "14881489614", "video_view_50p": 2777}, {"date": "2021-12-09 00:00:00+00:00", "conversions": 15.686012355933565, "ingestion_time": "2021-12-02T12:06:40.737Z", "channel": "GOOGLE", "agency_id": 79, "impressions": 4577, "line_id": "127284931385", "creative_id": "549225733886", "video_view_complete": 5768, "advertiser_id": 82, "account_id": "6472380435", "job_id": 1024, "spend": 1976480000, "video_view_25p": 1916, "clicks": 8423, "video_view_75p": 5003, "campaign_id": "14823424775", "video_view_50p": 1288}, {"date": "2021-12-09 00:00:00+00:00", "conversions": 81.64112200995378, "ingestion_time": "2021-12-02T12:06:40.737Z", "channel": "GOOGLE", "agency_id": 79, "impressions": 8213, "line_id": "127284931385", "creative_id": "549225733886", "video_view_complete": 3914, "advertiser_id": 82, "account_id": "6472380435", "job_id": 1024, "spend": 1976480000, "video_view_25p": 3699, "clicks": 7446, "video_view_75p": 1240, "campaign_id": "14823424775", "video_view_50p": 7185}, {"date": "2021-12-09 00:00:00+00:00", "conversions": 58.16335653159835, "ingestion_time": "2021-12-02T12:06:40.737Z", "channel": "GOOGLE", "agency_id": 79, "impressions": 8191, "line_id": "127284931385", "creative_id": "549225733877", "video_view_complete": 1193, "advertiser_id": 82, "account_id": "6472380435", "job_id": 1024, "spend": 1976480000, "video_view_25p": 6337, "clicks": 4335, "video_view_75p": 5692, "campaign_id": "14823424775", "video_view_50p": 5344}, {"date": "2021-12-09 00:00:00+00:00", "conversions": 4.525894508199002, "ingestion_time": "2021-12-02T12:06:40.737Z", "channel": "GOOGLE", "agency_id": 79, "impressions": 9471, "line_id": "127284931385", "creative_id": "549225733877", "video_view_complete": 4711, "advertiser_id": 82, "account_id": "6472380435", "job_id": 1024, "spend": 1976480000, "video_view_25p": 7966, "clicks": 360, "video_view_75p": 3500, "campaign_id": "14823424775", "video_view_50p": 1481}, {"date": "2021-12-09 00:00:00+00:00", "conversions": 33.184905880716144, "ingestion_time": "2021-12-02T12:06:40.737Z", "channel": "FACEBOOK", "agency_id": 79, "impressions": 4397, "line_id": "23849725967160369", "creative_id": "23849725967310369", "video_view_complete": 1368, "advertiser_id": 82, "account_id": "act_903970073442940", "job_id": 1024, "spend": 1976480000, "video_view_25p": 7889, "clicks": 5302, "video_view_75p": 453, "campaign_id": "23849725966810369", "video_view_50p": 2135}, {"date": "2021-12-09 00:00:00+00:00", "conversions": 71.97729055724972, "ingestion_time": "2021-12-02T12:06:40.737Z", "channel": "FACEBOOK", "agency_id": 79, "impressions": 5924, "line_id": "23849725967160369", "creative_id": "23849725967310369", "video_view_complete": 3297, "advertiser_id": 82, "account_id": "act_903970073442940", "job_id": 1024, "spend": 1976480000, "video_view_25p": 8605, "clicks": 6540, "video_view_75p": 7054, "campaign_id": "23849725966810369", "video_view_50p": 5439}, {"date": "2021-12-09 00:00:00+00:00", "conversions": 59.114884085399524, "ingestion_time": "2021-12-02T12:06:40.737Z", "channel": "FACEBOOK", "agency_id": 79, "impressions": 4560, "line_id": "23846437463260369", "creative_id": "23846437463280369", "video_view_complete": 9479, "advertiser_id": 82, "account_id": "act_903970073442940", "job_id": 1024, "spend": 1976480000, "video_view_25p": 5649, "clicks": 4306, "video_view_75p": 6785, "campaign_id": "23846437463240369", "video_view_50p": 1560}, {"date": "2021-12-09 00:00:00+00:00", "conversions": 36.5328995701668, "ingestion_time": "2021-12-02T12:06:40.737Z", "channel": "FACEBOOK", "agency_id": 79, "impressions": 2691, "line_id": "23846437463260369", "creative_id": "23846437463280369", "video_view_complete": 6988, "advertiser_id": 82, "account_id": "act_903970073442940", "job_id": 1024, "spend": 1976480000, "video_view_25p": 5201, "clicks": 698, "video_view_75p": 678, "campaign_id": "23846437463240369", "video_view_50p": 4697}, {"date": "2021-12-09 00:00:00+00:00", "conversions": 84.0127955250185, "ingestion_time": "2021-12-02T12:06:40.737Z", "channel": "FACEBOOK", "agency_id": 79, "impressions": 9964, "line_id": "23849765193950369", "creative_id": "23849765194020369", "video_view_complete": 8057, "advertiser_id": 82, "account_id": "act_903970073442940", "job_id": 1024, "spend": 1976480000, "video_view_25p": 8316, "clicks": 6424, "video_view_75p": 7237, "campaign_id": "23849765193560369", "video_view_50p": 4873}, {"date": "2021-12-09 00:00:00+00:00", "conversions": 96.06735226719186, "ingestion_time": "2021-12-02T12:06:40.737Z", "channel": "FACEBOOK", "agency_id": 79, "impressions": 2428, "line_id": "23849765193950369", "creative_id": "23849765194020369", "video_view_complete": 5310, "advertiser_id": 82, "account_id": "act_903970073442940", "job_id": 1024, "spend": 1976480000, "video_view_25p": 567, "clicks": 8634, "video_view_75p": 4241, "campaign_id": "23849765193560369", "video_view_50p": 5592}, {"date": "2021-12-09 00:00:00+00:00", "conversions": 95.60600937131265, "ingestion_time": "2021-12-02T12:06:40.737Z", "channel": "FACEBOOK", "agency_id": 79, "impressions": 6452, "line_id": "23845998298820213", "creative_id": "23845998784140213", "video_view_complete": 2907, "advertiser_id": 82, "account_id": "act_3427969697428048", "job_id": 1024, "spend": 1976480000, "video_view_25p": 4484, "clicks": 8100, "video_view_75p": 4824, "campaign_id": "23845998298760213", "video_view_50p": 9116}, {"date": "2021-12-09 00:00:00+00:00", "conversions": 14.001033870930934, "ingestion_time": "2021-12-02T12:06:40.737Z", "channel": "FACEBOOK", "agency_id": 79, "impressions": 6410, "line_id": "23845998298820213", "creative_id": "23845998784140213", "video_view_complete": 5544, "advertiser_id": 82, "account_id": "act_3427969697428048", "job_id": 1024, "spend": 1976480000, "video_view_25p": 4112, "clicks": 7863, "video_view_75p": 9118, "campaign_id": "23845998298760213", "video_view_50p": 2323}, {"date": "2021-12-09 00:00:00+00:00", "conversions": 80.91025831852575, "ingestion_time": "2021-12-02T12:06:40.737Z", "channel": "FACEBOOK", "agency_id": 79, "impressions": 5620, "line_id": "23849783566440369", "creative_id": "23849783566450369", "video_view_complete": 3288, "advertiser_id": 82, "account_id": "act_903970073442940", "job_id": 1024, "spend": 1976480000, "video_view_25p": 8458, "clicks": 3847, "video_view_75p": 8600, "campaign_id": "23849783518160369", "video_view_50p": 9414}, {"date": "2021-12-09 00:00:00+00:00", "conversions": 46.879422606718244, "ingestion_time": "2021-12-02T12:06:40.737Z", "channel": "FACEBOOK", "agency_id": 79, "impressions": 4060, "line_id": "23849783566440369", "creative_id": "23849783566450369", "video_view_complete": 8820, "advertiser_id": 82, "account_id": "act_903970073442940", "job_id": 1024, "spend": 1976480000, "video_view_25p": 856, "clicks": 5568, "video_view_75p": 8930, "campaign_id": "23849783518160369", "video_view_50p": 1783}, {"date": "2021-12-09 00:00:00+00:00", "conversions": 10.267904651183969, "ingestion_time": "2021-12-02T12:06:40.737Z", "channel": "FACEBOOK", "agency_id": 79, "impressions": 540, "line_id": "23845998298820213", "creative_id": "23845998298890213", "video_view_complete": 9720, "advertiser_id": 82, "account_id": "act_3427969697428048", "job_id": 1024, "spend": 1976480000, "video_view_25p": 2892, "clicks": 2240, "video_view_75p": 3353, "campaign_id": "23845998298760213", "video_view_50p": 9065}, {"date": "2021-12-09 00:00:00+00:00", "conversions": 93.326304823145, "ingestion_time": "2021-12-02T12:06:40.737Z", "channel": "FACEBOOK", "agency_id": 79, "impressions": 5214, "line_id": "23845998298820213", "creative_id": "23845998298890213", "video_view_complete": 8805, "advertiser_id": 82, "account_id": "act_3427969697428048", "job_id": 1024, "spend": 1976480000, "video_view_25p": 2993, "clicks": 3067, "video_view_75p": 5938, "campaign_id": "23845998298760213", "video_view_50p": 9495}]